[{"type":"sprite","x":0,"y":0,"name":"frame0","0":{"x":0,"y":0,"name":"step3","type":"sprite","r":0,"sx":1,"sy":1,"a":1,"skewX":0,"skewY":0,"0":{"x":475.05,"y":1218.2,"w":332.85,"h":70,"name":"txt0","type":"text","r":0,"txt":"土壤横截面","a":"center","f":"50px 'Microsoft YaHei'","c":"#FFFFFF"},"1":{"x":-330.7,"y":149.45,"name":"earth","type":"sprite","r":0,"sx":3.5,"sy":3.5,"a":1,"skewX":0,"skewY":0,"0":{"x":263.15,"y":141.1,"name":"antLabel","type":"sprite","r":0,"sx":1,"sy":1,"a":1,"skewX":0,"skewY":0,"0":{"type":"bitmap","libName":"antQipao","x":-43.45,"y":-115.5,"r":0,"sx":1,"sy":1,"skewX":0,"skewY":0}},"1":{"x":250.9,"y":142.1,"name":"ant","type":"nbMovie","r":0,"sx":0.4099884033203125,"sy":0.4099884033203125,"a":1,"skewX":0,"skewY":0,"0":{"index":1,"0":{"type":"bitmap","libName":"Bitmap 23","x":-28,"y":-36,"r":0,"sx":1,"sy":1,"skewX":0,"skewY":0}},"1":{"index":1,"0":{"type":"bitmap","libName":"Bitmap 24","x":-28,"y":-36,"r":0,"sx":1,"sy":1,"skewX":0,"skewY":0}},"2":{"index":1,"0":{"type":"bitmap","libName":"Bitmap 25","x":-28,"y":-36,"r":0,"sx":1,"sy":1,"skewX":0,"skewY":0}},"3":{"index":1,"0":{"type":"bitmap","libName":"Bitmap 26","x":-28,"y":-36,"r":0,"sx":1,"sy":1,"skewX":0,"skewY":0}},"4":{"index":1,"0":{"type":"bitmap","libName":"Bitmap 27","x":-28,"y":-36,"r":0,"sx":1,"sy":1,"skewX":0,"skewY":0}},"5":{"index":1,"0":{"type":"bitmap","libName":"Bitmap 28","x":-28,"y":-36,"r":0,"sx":1,"sy":1,"skewX":0,"skewY":0}},"6":{"index":1,"0":{"type":"bitmap","libName":"Bitmap 29","x":-28,"y":-36,"r":0,"sx":1,"sy":1,"skewX":0,"skewY":0}},"7":{"index":1,"0":{"type":"bitmap","libName":"Bitmap 30","x":-28,"y":-36,"r":0,"sx":1,"sy":1,"skewX":0,"skewY":0}},"8":{"index":1,"0":{"type":"bitmap","libName":"Bitmap 31","x":-28,"y":-36,"r":0,"sx":1,"sy":1,"skewX":0,"skewY":0}},"9":{"index":1,"0":{"type":"bitmap","libName":"Bitmap 32","x":-28,"y":-36,"r":0,"sx":1,"sy":1,"skewX":0,"skewY":0}}},"2":{"type":"bitmap","libName":"Bitmap 22","x":0.45,"y":0.35,"r":0,"sx":1,"sy":1,"skewX":0,"skewY":0},"3":{"x":336.35,"y":-18.55,"name":"j0","type":"sprite","r":0,"sx":1,"sy":1,"a":1,"skewX":0,"skewY":0},"4":{"x":267.85,"y":90.45,"name":"j2","type":"sprite","r":0,"sx":1,"sy":1,"a":1,"skewX":0,"skewY":0},"5":{"x":336.35,"y":42.45,"name":"j1","type":"sprite","r":0,"sx":1,"sy":1,"a":1,"skewX":0,"skewY":0},"6":{"x":151.4,"y":256.45,"name":"j9","type":"sprite","r":0,"sx":1,"sy":1,"a":1,"skewX":0,"skewY":0},"7":{"x":145.4,"y":130.55,"name":"j5","type":"sprite","r":0,"sx":1,"sy":1,"a":1,"skewX":0,"skewY":0},"8":{"x":208.85,"y":197.45,"name":"j7","type":"sprite","r":0,"sx":1,"sy":1,"a":1,"skewX":0,"skewY":0},"9":{"x":60.35,"y":267.45,"name":"j10","type":"sprite","r":0,"sx":1,"sy":1,"a":1,"skewX":0,"skewY":0},"10":{"x":37.85,"y":286.4,"name":"j11","type":"sprite","r":0,"sx":1,"sy":1,"a":1,"skewX":0,"skewY":0},"11":{"x":265.85,"y":34.45,"name":"j3","type":"sprite","r":0,"sx":1,"sy":1,"a":1,"skewX":0,"skewY":0},"12":{"x":49.9,"y":316.4,"name":"j12","type":"sprite","r":0,"sx":1,"sy":1,"a":1,"skewX":0,"skewY":0},"13":{"x":175.4,"y":71.45,"name":"j4","type":"sprite","r":0,"sx":1,"sy":1,"a":1,"skewX":0,"skewY":0},"14":{"x":151.4,"y":165.45,"name":"j6","type":"sprite","r":0,"sx":1,"sy":1,"a":1,"skewX":0,"skewY":0},"15":{"x":228.85,"y":233.45,"name":"j8","type":"sprite","r":0,"sx":1,"sy":1,"a":1,"skewX":0,"skewY":0},"16":{"x":486.25,"y":34.05,"name":"i1","type":"sprite","r":0,"sx":1,"sy":1,"a":1,"skewX":0,"skewY":0},"17":{"x":360.75,"y":80.05,"name":"i4","type":"sprite","r":0,"sx":1,"sy":1,"a":1,"skewX":0,"skewY":0},"18":{"x":476.7,"y":-10.15,"name":"i0","type":"sprite","r":0,"sx":1,"sy":1,"a":1,"skewX":0,"skewY":0},"19":{"x":445.2,"y":52.85,"name":"i2","type":"sprite","r":0,"sx":1,"sy":1,"a":1,"skewX":0,"skewY":0},"20":{"x":449.2,"y":147.25,"name":"i7","type":"sprite","r":0,"sx":1,"sy":1,"a":1,"skewX":0,"skewY":0},"21":{"x":336.9,"y":230.05,"name":"i10","type":"sprite","r":0,"sx":1,"sy":1,"a":1,"skewX":0,"skewY":0},"22":{"x":397.85,"y":48.85,"name":"i3","type":"sprite","r":0,"sx":1,"sy":1,"a":1,"skewX":0,"skewY":0},"23":{"x":360.75,"y":134.85,"name":"i5","type":"sprite","r":0,"sx":1,"sy":1,"a":1,"skewX":0,"skewY":0},"24":{"x":449.2,"y":188.45,"name":"i8","type":"sprite","r":0,"sx":1,"sy":1,"a":1,"skewX":0,"skewY":0},"25":{"x":269.75,"y":275.45,"name":"i12","type":"sprite","r":0,"sx":1,"sy":1,"a":1,"skewX":0,"skewY":0},"26":{"x":408.7,"y":154.25,"name":"i6","type":"sprite","r":0,"sx":1,"sy":1,"a":1,"skewX":0,"skewY":0},"27":{"x":397.85,"y":254.25,"name":"i9","type":"sprite","r":0,"sx":1,"sy":1,"a":1,"skewX":0,"skewY":0},"28":{"x":302.85,"y":318.2,"name":"i13","type":"sprite","r":0,"sx":1,"sy":1,"a":1,"skewX":0,"skewY":0},"29":{"x":292.35,"y":241.25,"name":"i11","type":"sprite","r":0,"sx":1,"sy":1,"a":1,"skewX":0,"skewY":0},"30":{"x":359.65,"y":135.45,"name":"h4","type":"sprite","r":0,"sx":1,"sy":1,"a":1,"skewX":0,"skewY":0},"31":{"x":568.8,"y":68.95,"name":"h0","type":"sprite","r":0,"sx":1,"sy":1,"a":1,"skewX":0,"skewY":0},"32":{"x":142.7,"y":128.55,"name":"h10","type":"sprite","r":0,"sx":1,"sy":1,"a":1,"skewX":0,"skewY":0},"33":{"x":268.15,"y":34.95,"name":"h8","type":"sprite","r":0,"sx":1,"sy":1,"a":1,"skewX":0,"skewY":0},"34":{"x":314.15,"y":139.95,"name":"h5","type":"sprite","r":0,"sx":1,"sy":1,"a":1,"skewX":0,"skewY":0},"35":{"x":504.3,"y":72.45,"name":"h1","type":"sprite","r":0,"sx":1,"sy":1,"a":1,"skewX":0,"skewY":0},"36":{"x":88.2,"y":155.75,"name":"h11","type":"sprite","r":0,"sx":1,"sy":1,"a":1,"skewX":0,"skewY":0},"37":{"x":189.7,"y":59.45,"name":"h9","type":"sprite","r":0,"sx":1,"sy":1,"a":1,"skewX":0,"skewY":0},"38":{"x":272.15,"y":185.2,"name":"h6","type":"sprite","r":0,"sx":1,"sy":1,"a":1,"skewX":0,"skewY":0},"39":{"x":478.3,"y":127.55,"name":"h2","type":"sprite","r":0,"sx":1,"sy":1,"a":1,"skewX":0,"skewY":0},"40":{"x":49.35,"y":186.7,"name":"h12","type":"sprite","r":0,"sx":1,"sy":1,"a":1,"skewX":0,"skewY":0},"41":{"x":253.65,"y":139.95,"name":"h7","type":"sprite","r":0,"sx":1,"sy":1,"a":1,"skewX":0,"skewY":0},"42":{"x":434.8,"y":152.2,"name":"h3","type":"sprite","r":0,"sx":1,"sy":1,"a":1,"skewX":0,"skewY":0},"43":{"x":-12.3,"y":180.2,"name":"h13","type":"sprite","r":0,"sx":1,"sy":1,"a":1,"skewX":0,"skewY":0},"44":{"x":-27.65,"y":119.4,"name":"g19","type":"sprite","r":0,"sx":1,"sy":1,"a":1,"skewX":0,"skewY":0},"45":{"x":16.9,"y":119.95,"name":"g17","type":"sprite","r":0,"sx":1,"sy":1,"a":1,"skewX":0,"skewY":0},"46":{"x":73.35,"y":101.45,"name":"g16","type":"sprite","r":0,"sx":1,"sy":1,"a":1,"skewX":0,"skewY":0},"47":{"x":567.8,"y":209,"name":"g0","type":"sprite","r":0,"sx":1,"sy":1,"a":1,"skewX":0,"skewY":0},"48":{"x":508.65,"y":209,"name":"g1","type":"sprite","r":0,"sx":1,"sy":1,"a":1,"skewX":0,"skewY":0},"49":{"x":434.8,"y":261.95,"name":"g4","type":"sprite","r":0,"sx":1,"sy":1,"a":1,"skewX":0,"skewY":0},"50":{"x":336.65,"y":229.95,"name":"g6","type":"sprite","r":0,"sx":1,"sy":1,"a":1,"skewX":0,"skewY":0},"51":{"x":486.2,"y":240,"name":"g2","type":"sprite","r":0,"sx":1,"sy":1,"a":1,"skewX":0,"skewY":0},"52":{"x":457.05,"y":242,"name":"g3","type":"sprite","r":0,"sx":1,"sy":1,"a":1,"skewX":0,"skewY":0},"53":{"x":229.25,"y":234,"name":"g7","type":"sprite","r":0,"sx":1,"sy":1,"a":1,"skewX":0,"skewY":0},"54":{"x":210.85,"y":49.95,"name":"g11","type":"sprite","r":0,"sx":1,"sy":1,"a":1,"skewX":0,"skewY":0},"55":{"x":374.8,"y":251.45,"name":"g5","type":"sprite","r":0,"sx":1,"sy":1,"a":1,"skewX":0,"skewY":0},"56":{"x":160.7,"y":88.45,"name":"g10","type":"sprite","r":0,"sx":1,"sy":1,"a":1,"skewX":0,"skewY":0},"57":{"x":147.85,"y":161.4,"name":"g9","type":"sprite","r":0,"sx":1,"sy":1,"a":1,"skewX":0,"skewY":0},"58":{"x":117.55,"y":71.5,"name":"g15","type":"sprite","r":0,"sx":1,"sy":1,"a":1,"skewX":0,"skewY":0},"59":{"x":210.85,"y":196.45,"name":"g8","type":"sprite","r":0,"sx":1,"sy":1,"a":1,"skewX":0,"skewY":0},"60":{"x":261.25,"y":31.65,"name":"g12","type":"sprite","r":0,"sx":1,"sy":1,"a":1,"skewX":0,"skewY":0},"61":{"x":185.85,"y":32.95,"name":"g14","type":"sprite","r":0,"sx":1,"sy":1,"a":1,"skewX":0,"skewY":0},"62":{"x":233.1,"y":18.75,"name":"g13","type":"sprite","r":0,"sx":1,"sy":1,"a":1,"skewX":0,"skewY":0},"63":{"x":481.8,"y":265.9,"name":"f1","type":"sprite","r":0,"sx":1,"sy":1,"a":1,"skewX":0,"skewY":0},"64":{"x":545.3,"y":324.25,"name":"f0","type":"sprite","r":0,"sx":1,"sy":1,"a":1,"skewX":0,"skewY":0},"65":{"x":382.3,"y":253.65,"name":"f2","type":"sprite","r":0,"sx":1,"sy":1,"a":1,"skewX":0,"skewY":0},"66":{"x":73.35,"y":227.25,"name":"f7","type":"sprite","r":0,"sx":1,"sy":1,"a":1,"skewX":0,"skewY":0},"67":{"x":330.75,"y":227.25,"name":"f3","type":"sprite","r":0,"sx":1,"sy":1,"a":1,"skewX":0,"skewY":0},"68":{"x":58.1,"y":181.45,"name":"f8","type":"sprite","r":0,"sx":1,"sy":1,"a":1,"skewX":0,"skewY":0},"69":{"x":231.1,"y":232.6,"name":"f4","type":"sprite","r":0,"sx":1,"sy":1,"a":1,"skewX":0,"skewY":0},"70":{"x":24.25,"y":190.45,"name":"f9","type":"sprite","r":0,"sx":1,"sy":1,"a":1,"skewX":0,"skewY":0},"71":{"x":155.55,"y":255.65,"name":"f5","type":"sprite","r":0,"sx":1,"sy":1,"a":1,"skewX":0,"skewY":0},"72":{"x":-25.65,"y":173.4,"name":"f10","type":"sprite","r":0,"sx":1,"sy":1,"a":1,"skewX":0,"skewY":0},"73":{"x":55.1,"y":265.9,"name":"f6","type":"sprite","r":0,"sx":1,"sy":1,"a":1,"skewX":0,"skewY":0},"74":{"x":-37.35,"y":121.35,"name":"e14","type":"sprite","r":0,"sx":1,"sy":1,"a":1,"skewX":0,"skewY":0},"75":{"x":22.5,"y":114.7,"name":"e13","type":"sprite","r":0,"sx":1,"sy":1,"a":1,"skewX":0,"skewY":0},"76":{"x":255.25,"y":31.1,"name":"e8","type":"sprite","r":0,"sx":1,"sy":1,"a":1,"skewX":0,"skewY":0},"77":{"x":175.5,"y":39.65,"name":"e10","type":"sprite","r":0,"sx":1,"sy":1,"a":1,"skewX":0,"skewY":0},"78":{"x":120.4,"y":65.95,"name":"e11","type":"sprite","r":0,"sx":1,"sy":1,"a":1,"skewX":0,"skewY":0},"79":{"x":226.7,"y":20.75,"name":"e9","type":"sprite","r":0,"sx":1,"sy":1,"a":1,"skewX":0,"skewY":0},"80":{"x":69.5,"y":105.3,"name":"e12","type":"sprite","r":0,"sx":1,"sy":1,"a":1,"skewX":0,"skewY":0},"81":{"x":231.1,"y":232.6,"name":"e3","type":"sprite","r":0,"sx":1,"sy":1,"a":1,"skewX":0,"skewY":0},"82":{"x":201,"y":54.7,"name":"e7","type":"sprite","r":0,"sx":1,"sy":1,"a":1,"skewX":0,"skewY":0},"83":{"x":270.35,"y":275.6,"name":"e1","type":"sprite","r":0,"sx":1,"sy":1,"a":1,"skewX":0,"skewY":0},"84":{"x":149,"y":163.45,"name":"e5","type":"sprite","r":0,"sx":1,"sy":1,"a":1,"skewX":0,"skewY":0},"85":{"x":304.65,"y":230.6,"name":"e2","type":"sprite","r":0,"sx":1,"sy":1,"a":1,"skewX":0,"skewY":0},"86":{"x":155,"y":101.45,"name":"e6","type":"sprite","r":0,"sx":1,"sy":1,"a":1,"skewX":0,"skewY":0},"87":{"x":306.65,"y":324.25,"name":"e0","type":"sprite","r":0,"sx":1,"sy":1,"a":1,"skewX":0,"skewY":0},"88":{"x":207.05,"y":194.8,"name":"e4","type":"sprite","r":0,"sx":1,"sy":1,"a":1,"skewX":0,"skewY":0},"89":{"x":229.1,"y":231.6,"name":"d2","type":"sprite","r":0,"sx":1,"sy":1,"a":1,"skewX":0,"skewY":0},"90":{"x":47.9,"y":326.25,"name":"d0","type":"sprite","r":0,"sx":1,"sy":1,"a":1,"skewX":0,"skewY":0},"91":{"x":330.75,"y":227.25,"name":"d3","type":"sprite","r":0,"sx":1,"sy":1,"a":1,"skewX":0,"skewY":0},"92":{"x":44.9,"y":274.9,"name":"d1","type":"sprite","r":0,"sx":1,"sy":1,"a":1,"skewX":0,"skewY":0},"93":{"x":449.25,"y":147.45,"name":"d6","type":"sprite","r":0,"sx":1,"sy":1,"a":1,"skewX":0,"skewY":0},"94":{"x":402.2,"y":253.65,"name":"d4","type":"sprite","r":0,"sx":1,"sy":1,"a":1,"skewX":0,"skewY":0},"95":{"x":409.75,"y":154.45,"name":"d7","type":"sprite","r":0,"sx":1,"sy":1,"a":1,"skewX":0,"skewY":0},"96":{"x":450.7,"y":182.45,"name":"d5","type":"sprite","r":0,"sx":1,"sy":1,"a":1,"skewX":0,"skewY":0},"97":{"x":478.8,"y":42.75,"name":"d11","type":"sprite","r":0,"sx":1,"sy":1,"a":1,"skewX":0,"skewY":0},"98":{"x":359.2,"y":134.45,"name":"d8","type":"sprite","r":0,"sx":1,"sy":1,"a":1,"skewX":0,"skewY":0},"99":{"x":488.75,"y":13.5,"name":"d12","type":"sprite","r":0,"sx":1,"sy":1,"a":1,"skewX":0,"skewY":0},"100":{"x":394.7,"y":50.35,"name":"d10","type":"sprite","r":0,"sx":1,"sy":1,"a":1,"skewX":0,"skewY":0},"101":{"x":359.2,"y":80.45,"name":"d9","type":"sprite","r":0,"sx":1,"sy":1,"a":1,"skewX":0,"skewY":0},"102":{"x":458.7,"y":-17.05,"name":"d13","type":"sprite","r":0,"sx":1,"sy":1,"a":1,"skewX":0,"skewY":0},"103":{"x":208.05,"y":133.45,"name":"c7","type":"sprite","r":0,"sx":1,"sy":1,"a":1,"skewX":0,"skewY":0},"104":{"x":209.05,"y":101.45,"name":"c6","type":"sprite","r":0,"sx":1,"sy":1,"a":1,"skewX":0,"skewY":0},"105":{"x":169.55,"y":80.45,"name":"c5","type":"sprite","r":0,"sx":1,"sy":1,"a":1,"skewX":0,"skewY":0},"106":{"x":145.9,"y":128.55,"name":"c4","type":"sprite","r":0,"sx":1,"sy":1,"a":1,"skewX":0,"skewY":0},"107":{"x":103.5,"y":145.45,"name":"c3","type":"sprite","r":0,"sx":1,"sy":1,"a":1,"skewX":0,"skewY":0},"108":{"x":60.1,"y":187.45,"name":"c2","type":"sprite","r":0,"sx":1,"sy":1,"a":1,"skewX":0,"skewY":0},"109":{"x":-0.3,"y":184.45,"name":"c1","type":"sprite","r":0,"sx":1,"sy":1,"a":1,"skewX":0,"skewY":0},"110":{"x":-18.25,"y":184.45,"name":"c0","type":"sprite","r":0,"sx":1,"sy":1,"a":1,"skewX":0,"skewY":0},"111":{"x":273.5,"y":184.45,"name":"c10","type":"sprite","r":0,"sx":1,"sy":1,"a":1,"skewX":0,"skewY":0},"112":{"x":321,"y":136.45,"name":"c11","type":"sprite","r":0,"sx":1,"sy":1,"a":1,"skewX":0,"skewY":0},"113":{"x":216.55,"y":156.75,"name":"c8","type":"sprite","r":0,"sx":1,"sy":1,"a":1,"skewX":0,"skewY":0},"114":{"x":253.85,"y":163.45,"name":"c9","type":"sprite","r":0,"sx":1,"sy":1,"a":1,"skewX":0,"skewY":0},"115":{"x":410.45,"y":153.75,"name":"c12","type":"sprite","r":0,"sx":1,"sy":1,"a":1,"skewX":0,"skewY":0},"116":{"x":478.8,"y":131.45,"name":"c13","type":"sprite","r":0,"sx":1,"sy":1,"a":1,"skewX":0,"skewY":0},"117":{"x":503.3,"y":71.45,"name":"c14","type":"sprite","r":0,"sx":1,"sy":1,"a":1,"skewX":0,"skewY":0},"118":{"x":567.7,"y":69.45,"name":"c15","type":"sprite","r":0,"sx":1,"sy":1,"a":1,"skewX":0,"skewY":0},"119":{"x":344.35,"y":4.95,"name":"b10","type":"sprite","r":0,"sx":1,"sy":1,"a":1,"skewX":0,"skewY":0},"120":{"x":338.6,"y":42.75,"name":"b9","type":"sprite","r":0,"sx":1,"sy":1,"a":1,"skewX":0,"skewY":0},"121":{"x":304.65,"y":77.3,"name":"b8","type":"sprite","r":0,"sx":1,"sy":1,"a":1,"skewX":0,"skewY":0},"122":{"x":269.5,"y":86.3,"name":"b7","type":"sprite","r":0,"sx":1,"sy":1,"a":1,"skewX":0,"skewY":0},"123":{"x":269.5,"y":34.45,"name":"b6","type":"sprite","r":0,"sx":1,"sy":1,"a":1,"skewX":0,"skewY":0},"124":{"x":249.6,"y":24.8,"name":"b5","type":"sprite","r":0,"sx":1,"sy":1,"a":1,"skewX":0,"skewY":0},"125":{"x":163.9,"y":39.55,"name":"b4","type":"sprite","r":0,"sx":1,"sy":1,"a":1,"skewX":0,"skewY":0},"126":{"x":97.3,"y":91.3,"name":"b3","type":"sprite","r":0,"sx":1,"sy":1,"a":1,"skewX":0,"skewY":0},"127":{"x":42.9,"y":111.2,"name":"b2","type":"sprite","r":0,"sx":1,"sy":1,"a":1,"skewX":0,"skewY":0},"128":{"x":-0.3,"y":123.05,"name":"b1","type":"sprite","r":0,"sx":1,"sy":1,"a":1,"skewX":0,"skewY":0},"129":{"x":-11.5,"y":123.05,"name":"b0","type":"sprite","r":0,"sx":1,"sy":1,"a":1,"skewX":0,"skewY":0},"130":{"x":1.95,"y":117.4,"name":"a8","type":"sprite","r":0,"sx":1,"sy":1,"a":1,"skewX":0,"skewY":0},"131":{"x":37.35,"y":116.7,"name":"a7","type":"sprite","r":0,"sx":1,"sy":1,"a":1,"skewX":0,"skewY":0},"132":{"x":77.2,"y":98,"name":"a6","type":"sprite","r":0,"sx":1,"sy":1,"a":1,"skewX":0,"skewY":0},"133":{"x":55.1,"y":61.15,"name":"a5","type":"sprite","r":0,"sx":1,"sy":1,"a":1,"skewX":0,"skewY":0},"134":{"x":20.25,"y":58.7,"name":"a4","type":"sprite","r":0,"sx":1,"sy":1,"a":1,"skewX":0,"skewY":0},"135":{"x":8.4,"y":51.35,"name":"a3","type":"sprite","r":0,"sx":1,"sy":1,"a":1,"skewX":0,"skewY":0},"136":{"x":3.5,"y":25.95,"name":"a2","type":"sprite","r":0,"sx":1,"sy":1,"a":1,"skewX":0,"skewY":0},"137":{"x":-0.3,"y":13.5,"name":"a1","type":"sprite","r":0,"sx":1,"sy":1,"a":1,"skewX":0,"skewY":0},"138":{"x":-18.25,"y":13.5,"name":"a0","type":"sprite","r":0,"sx":1,"sy":1,"a":1,"skewX":0,"skewY":0},"139":{"type":"bitmap","libName":"Bitmap 21","x":0,"y":0,"r":0,"sx":1,"sy":1,"skewX":0,"skewY":0},"140":{"x":0,"y":0,"name":"antMask","type":"sprite","r":0,"sx":2.2826385498046875,"sy":3.7283935546875,"a":1,"skewX":0,"skewY":0,"0":{"type":"shape","path":[255,0,240.95,2,81,240.95,2,81,0,2,0,0,2,0,240.95,2,0,240.95,1,1,65280,33]}}}},"1":{"x":0,"y":0,"name":"step2","type":"sprite","r":0,"sx":1,"sy":1,"a":1,"skewX":0,"skewY":0,"0":{"x":664.25,"y":602.45,"name":"bean","type":"nbMovie","r":0,"sx":2.7562255859375,"sy":2.7562255859375,"a":1,"skewX":0,"skewY":0,"0":{"index":0},"1":{"index":1,"0":{"type":"bitmap","libName":"Bitmap 109","x":6.15,"y":-1.45,"r":0,"sx":0.2828826904296875,"sy":0.2828826904296875,"skewX":0,"skewY":0}},"2":{"index":1,"0":{"type":"bitmap","libName":"Bitmap 108","x":6.15,"y":-1.45,"r":0,"sx":0.2828826904296875,"sy":0.2828826904296875,"skewX":0,"skewY":0}},"3":{"index":1,"0":{"type":"bitmap","libName":"Bitmap 107","x":3.9,"y":-1.45,"r":0,"sx":0.2828826904296875,"sy":0.2828826904296875,"skewX":0,"skewY":0}},"4":{"index":1,"0":{"type":"bitmap","libName":"Bitmap 106","x":3.9,"y":-1.45,"r":0,"sx":0.2828826904296875,"sy":0.2828826904296875,"skewX":0,"skewY":0}},"5":{"index":1,"0":{"type":"bitmap","libName":"Bitmap 105","x":2.95,"y":-1.45,"r":0,"sx":0.2828826904296875,"sy":0.2828826904296875,"skewX":0,"skewY":0}},"6":{"index":1,"0":{"type":"bitmap","libName":"Bitmap 104","x":2.95,"y":-1.45,"r":0,"sx":0.2828826904296875,"sy":0.2828826904296875,"skewX":0,"skewY":0}},"7":{"index":1,"0":{"type":"bitmap","libName":"Bitmap 103","x":-0.35,"y":-2.15,"r":0,"sx":0.2828826904296875,"sy":0.2828826904296875,"skewX":0,"skewY":0}},"8":{"index":1,"0":{"type":"bitmap","libName":"Bitmap 100","x":-10.6,"y":-3.35,"r":0,"sx":0.2828826904296875,"sy":0.2828826904296875,"skewX":0,"skewY":0}},"9":{"index":1,"0":{"type":"bitmap","libName":"Bitmap 99","x":-10.7,"y":-3.35,"r":0,"sx":0.2828826904296875,"sy":0.2828826904296875,"skewX":0,"skewY":0}},"10":{"index":1,"0":{"type":"bitmap","libName":"Bitmap 98","x":-10.85,"y":-3.35,"r":0,"sx":0.2828826904296875,"sy":0.2828826904296875,"skewX":0,"skewY":0}},"11":{"index":1,"0":{"type":"bitmap","libName":"Bitmap 97","x":-10.95,"y":-3.3,"r":0,"sx":0.2828826904296875,"sy":0.2828826904296875,"skewX":0,"skewY":0}},"12":{"index":1,"0":{"type":"bitmap","libName":"Bitmap 96","x":-11.1,"y":-3.3,"r":0,"sx":0.2828826904296875,"sy":0.2828826904296875,"skewX":0,"skewY":0}},"13":{"index":1,"0":{"type":"bitmap","libName":"Bitmap 95","x":-11.2,"y":-3.3,"r":0,"sx":0.2828826904296875,"sy":0.2828826904296875,"skewX":0,"skewY":0}},"14":{"index":1,"0":{"type":"bitmap","libName":"Bitmap 94","x":-11.3,"y":-3.3,"r":0,"sx":0.2828826904296875,"sy":0.2828826904296875,"skewX":0,"skewY":0}},"15":{"index":1,"0":{"type":"bitmap","libName":"Bitmap 93","x":-11.4,"y":-3.9,"r":0,"sx":0.2828826904296875,"sy":0.2828826904296875,"skewX":0,"skewY":0}},"16":{"index":1,"0":{"type":"bitmap","libName":"Bitmap 92","x":-11.45,"y":-3.95,"r":0,"sx":0.2828826904296875,"sy":0.2828826904296875,"skewX":0,"skewY":0}},"17":{"index":1,"0":{"type":"bitmap","libName":"Bitmap 91","x":-11.6,"y":-4.05,"r":0,"sx":0.2828826904296875,"sy":0.2828826904296875,"skewX":0,"skewY":0}},"18":{"index":1,"0":{"type":"bitmap","libName":"Bitmap 90","x":-11.7,"y":-4.2,"r":0,"sx":0.2828826904296875,"sy":0.2828826904296875,"skewX":0,"skewY":0}},"19":{"index":1,"0":{"type":"bitmap","libName":"Bitmap 89","x":-11.7,"y":-4.4,"r":0,"sx":0.2828826904296875,"sy":0.2828826904296875,"skewX":0,"skewY":0}},"20":{"index":1,"0":{"type":"bitmap","libName":"Bitmap 88","x":-11.8,"y":-4.6,"r":0,"sx":0.2828826904296875,"sy":0.2828826904296875,"skewX":0,"skewY":0}},"21":{"index":1,"0":{"type":"bitmap","libName":"Bitmap 87","x":-11.9,"y":-4.9,"r":0,"sx":0.2828826904296875,"sy":0.2828826904296875,"skewX":0,"skewY":0}},"22":{"index":1,"0":{"type":"bitmap","libName":"Bitmap 86","x":-11.95,"y":-5.3,"r":0,"sx":0.2828826904296875,"sy":0.2828826904296875,"skewX":0,"skewY":0}},"23":{"index":1,"0":{"type":"bitmap","libName":"Bitmap 85","x":-12.05,"y":-5.8,"r":0,"sx":0.2828826904296875,"sy":0.2828826904296875,"skewX":0,"skewY":0}},"24":{"index":1,"0":{"type":"bitmap","libName":"Bitmap 84","x":-12.05,"y":-6.3,"r":0,"sx":0.2828826904296875,"sy":0.2828826904296875,"skewX":0,"skewY":0}},"25":{"index":1,"0":{"type":"bitmap","libName":"Bitmap 83","x":-12.15,"y":-6.75,"r":0,"sx":0.2828826904296875,"sy":0.2828826904296875,"skewX":0,"skewY":0}},"26":{"index":1,"0":{"type":"bitmap","libName":"Bitmap 82","x":-12.2,"y":-7.25,"r":0,"sx":0.2828826904296875,"sy":0.2828826904296875,"skewX":0,"skewY":0}},"27":{"index":1,"0":{"type":"bitmap","libName":"Bitmap 81","x":-12.2,"y":-7.25,"r":0,"sx":0.2828826904296875,"sy":0.2828826904296875,"skewX":0,"skewY":0}},"28":{"index":1,"0":{"type":"bitmap","libName":"Bitmap 80","x":-12.25,"y":-7.25,"r":0,"sx":0.2828826904296875,"sy":0.2828826904296875,"skewX":0,"skewY":0}},"29":{"index":1,"0":{"type":"bitmap","libName":"Bitmap 79","x":-12.3,"y":-7.25,"r":0,"sx":0.2828826904296875,"sy":0.2828826904296875,"skewX":0,"skewY":0}},"30":{"index":1,"0":{"type":"bitmap","libName":"Bitmap 78","x":-12.3,"y":-7.25,"r":0,"sx":0.2828826904296875,"sy":0.2828826904296875,"skewX":0,"skewY":0}},"31":{"index":1,"0":{"type":"bitmap","libName":"Bitmap 77","x":-12.35,"y":-7.25,"r":0,"sx":0.2828826904296875,"sy":0.2828826904296875,"skewX":0,"skewY":0}},"32":{"index":1,"0":{"type":"bitmap","libName":"Bitmap 76","x":-12.4,"y":-7.25,"r":0,"sx":0.2828826904296875,"sy":0.2828826904296875,"skewX":0,"skewY":0}},"33":{"index":1,"0":{"type":"bitmap","libName":"Bitmap 75","x":-12.45,"y":-7.25,"r":0,"sx":0.2828826904296875,"sy":0.2828826904296875,"skewX":0,"skewY":0}},"34":{"index":1,"0":{"type":"bitmap","libName":"Bitmap 74","x":-12.45,"y":-8.45,"r":0,"sx":0.2828826904296875,"sy":0.2828826904296875,"skewX":0,"skewY":0}},"35":{"index":1,"0":{"type":"bitmap","libName":"Bitmap 73","x":-12.5,"y":-9.55,"r":0,"sx":0.2828826904296875,"sy":0.2828826904296875,"skewX":0,"skewY":0}},"36":{"index":1,"0":{"type":"bitmap","libName":"Bitmap 72","x":-12.55,"y":-10.7,"r":0,"sx":0.2828826904296875,"sy":0.2828826904296875,"skewX":0,"skewY":0}},"37":{"index":1,"0":{"type":"bitmap","libName":"Bitmap 71","x":-12.55,"y":-11.85,"r":0,"sx":0.2828826904296875,"sy":0.2828826904296875,"skewX":0,"skewY":0}},"38":{"index":1,"0":{"type":"bitmap","libName":"Bitmap 70","x":-12.55,"y":-13,"r":0,"sx":0.2828826904296875,"sy":0.2828826904296875,"skewX":0,"skewY":0}},"39":{"index":1,"0":{"type":"bitmap","libName":"Bitmap 69","x":-12.6,"y":-14.1,"r":0,"sx":0.2828826904296875,"sy":0.2828826904296875,"skewX":0,"skewY":0}},"40":{"index":1,"0":{"type":"bitmap","libName":"Bitmap 68","x":-12.6,"y":-15.2,"r":0,"sx":0.2828826904296875,"sy":0.2828826904296875,"skewX":0,"skewY":0}},"41":{"index":1,"0":{"type":"bitmap","libName":"Bitmap 67","x":-12.6,"y":-16.25,"r":0,"sx":0.2828826904296875,"sy":0.2828826904296875,"skewX":0,"skewY":0}},"42":{"index":1,"0":{"type":"bitmap","libName":"Bitmap 66","x":-12.6,"y":-17.25,"r":0,"sx":0.2828826904296875,"sy":0.2828826904296875,"skewX":0,"skewY":0}},"43":{"index":1,"0":{"type":"bitmap","libName":"Bitmap 65","x":-12.65,"y":-18.2,"r":0,"sx":0.2828826904296875,"sy":0.2828826904296875,"skewX":0,"skewY":0}},"44":{"index":1,"0":{"type":"bitmap","libName":"Bitmap 64","x":-12.7,"y":-19.05,"r":0,"sx":0.2828826904296875,"sy":0.2828826904296875,"skewX":0,"skewY":0}},"45":{"index":1,"0":{"type":"bitmap","libName":"Bitmap 63","x":-12.7,"y":-19.95,"r":0,"sx":0.2828826904296875,"sy":0.2828826904296875,"skewX":0,"skewY":0}}},"1":{"type":"bitmap","libName":"Bitmap 141","x":367.2,"y":552.5,"r":0,"sx":1,"sy":1,"skewX":0,"skewY":0},"2":{"x":559,"y":760.9,"w":251.1,"h":70,"name":"","type":"text","r":0,"txt":"石膏糊","a":"center","f":"50px 'Microsoft YaHei'","c":"#FFFFFF"},"3":{"x":711.15,"y":1170.1,"name":"timeline","type":"sprite","r":0,"sx":1,"sy":1,"a":1,"skewX":0,"skewY":0,"0":{"x":-452.5,"y":-254.9,"name":"drag","type":"sprite","r":0,"sx":1,"sy":1,"a":1,"skewX":0,"skewY":0,"0":{"x":20.4,"y":20.9,"name":"line1","type":"sprite","r":0,"sx":1,"sy":1,"a":1,"skewX":0,"skewY":0,"0":{"type":"bitmap","libName":"timeline_bBitmap 10new","x":-3.65,"y":-7,"r":0,"sx":1,"sy":1,"skewX":0,"skewY":0}},"1":{"x":20.35,"y":20.2,"name":"line0","type":"sprite","r":0,"sx":1,"sy":1,"a":1,"skewX":0,"skewY":0,"0":{"type":"bitmap","libName":"timeline_bBitmap 6new","x":-7.35,"y":-31.7,"r":0,"sx":2,"sy":2,"skewX":0,"skewY":0}},"2":{"type":"bitmap","libName":"timeline_bBitmap 28new","x":-18.05,"y":-21,"r":0,"sx":2,"sy":2,"skewX":0,"skewY":0}},"1":{"x":-431.2,"y":-237.9,"name":"bgMask","type":"sprite","r":0,"sx":0.6183929443359375,"sy":1,"a":1,"skewX":0,"skewY":0,"0":{"type":"shape","path":[255,-24.8,1328.95,2,28.2,1328.95,2,28.2,0,2,-24.8,0,2,-24.8,0.7,2,-24.8,1022.6,2,-24.8,1328.95,2,-24.8,1328.95,1,1,15066597,33,255,-24.85,1022.6,2,-24.8,1022.6,2,-24.8,0.7,2,-24.85,0.7,2,-24.85,1022.6,2,-24.85,1022.6,1,1,16777215,1,32]}},"2":{"x":-470.6,"y":-188.95,"w":83.5,"h":70,"name":"","type":"text","r":0,"txt":"0天","a":"center","f":"50px 'Microsoft YaHei'","c":"#FFFFFF"},"3":{"x":338.05,"y":-196.8,"w":83.5,"h":70,"name":"","type":"text","r":0,"txt":"2周","a":"center","f":"50px 'Microsoft YaHei'","c":"#FFFFFF"},"4":{"x":354.4,"y":-257.95,"name":"a1","type":"sprite","r":0,"sx":1,"sy":1,"a":1,"skewX":0,"skewY":0,"0":{"type":"bitmap","libName":"timeline_bhitArea","x":-24.5,"y":-23,"r":0,"sx":1.8399658203125,"sy":1.8399658203125,"skewX":0,"skewY":0},"1":{"type":"bitmap","libName":"timeline_bBitmap 1fu","x":0,"y":4.75,"r":0,"sx":2,"sy":2,"skewX":0,"skewY":0}},"5":{"x":-452.5,"y":-257.95,"name":"a0","type":"sprite","r":0,"sx":1,"sy":1,"a":1,"skewX":0,"skewY":0,"0":{"type":"bitmap","libName":"timeline_bhitArea","x":-24.5,"y":-23,"r":0,"sx":1.8399658203125,"sy":1.8399658203125,"skewX":0,"skewY":0},"1":{"type":"bitmap","libName":"timeline_bBitmap 1fu","x":0,"y":4.75,"r":0,"sx":2,"sy":2,"skewX":0,"skewY":0}},"6":{"x":-426.15,"y":-245.95,"name":"progressBar","type":"sprite","r":0,"sx":0.5623931884765625,"sy":1,"a":1,"skewX":0,"skewY":0,"0":{"type":"bitmap","libName":"timeline_byellow","x":0,"y":0,"r":0,"sx":1,"sy":1,"skewX":0,"skewY":0}},"7":{"type":"bitmap","libName":"timeline_bBitmap 88","x":-434.8,"y":-245.25,"r":0,"sx":0.568206787109375,"sy":1,"skewX":0,"skewY":0}}},"2":{"x":0,"y":0,"name":"step1","type":"sprite","r":0,"sx":1,"sy":1,"a":1,"skewX":0,"skewY":0,"0":{"x":897.5,"y":917.9,"w":84.2,"h":56.75,"name":"txt1","type":"text","r":0,"txt":"石头","a":"center","f":"40px 'Microsoft YaHei'","c":"#FFFFFF"},"1":{"x":354.6,"y":917.9,"w":124.2,"h":56.75,"name":"txt0","type":"text","r":0,"txt":"塑料瓶","a":"center","f":"40px 'Microsoft YaHei'","c":"#FFFFFF"},"2":{"x":685.4,"y":1287.95,"name":"timeline","type":"sprite","r":0,"sx":1,"sy":1,"a":1,"skewX":0,"skewY":0,"0":{"x":-452.5,"y":-254.9,"name":"drag","type":"sprite","r":0,"sx":1,"sy":1,"a":1,"skewX":0,"skewY":0,"0":{"x":20.4,"y":20.9,"name":"line1","type":"sprite","r":0,"sx":1,"sy":1,"a":1,"skewX":0,"skewY":0,"0":{"type":"bitmap","libName":"timeline_bBitmap 10new","x":-3.65,"y":-7,"r":0,"sx":1,"sy":1,"skewX":0,"skewY":0}},"1":{"x":20.35,"y":20.2,"name":"line0","type":"sprite","r":0,"sx":1,"sy":1,"a":1,"skewX":0,"skewY":0,"0":{"type":"bitmap","libName":"timeline_bBitmap 6new","x":-7.35,"y":-31.7,"r":0,"sx":2,"sy":2,"skewX":0,"skewY":0}},"2":{"type":"bitmap","libName":"timeline_bBitmap 28new","x":-18.05,"y":-21,"r":0,"sx":2,"sy":2,"skewX":0,"skewY":0}},"1":{"x":-431.2,"y":-237.9,"name":"bgMask","type":"sprite","r":0,"sx":0.6183929443359375,"sy":1,"a":1,"skewX":0,"skewY":0,"0":{"type":"shape","path":[255,-24.8,1328.95,2,28.2,1328.95,2,28.2,0,2,-24.8,0,2,-24.8,0.7,2,-24.8,1022.6,2,-24.8,1328.95,2,-24.8,1328.95,1,1,15066597,33,255,-24.85,1022.6,2,-24.8,1022.6,2,-24.8,0.7,2,-24.85,0.7,2,-24.85,1022.6,2,-24.85,1022.6,1,1,16777215,1,32]}},"2":{"x":-480.95,"y":-188.95,"w":104.2,"h":70,"name":"","type":"text","r":0,"txt":"开始","a":"center","f":"50px 'Microsoft YaHei'","c":"#FFFFFF"},"3":{"x":304.95,"y":-196.8,"w":144.8,"h":70,"name":"","type":"text","r":0,"txt":"第N年","a":"center","f":"50px 'Microsoft YaHei'","c":"#FFFFFF"},"4":{"x":354.4,"y":-257.95,"name":"a1","type":"sprite","r":0,"sx":1,"sy":1,"a":1,"skewX":0,"skewY":0,"0":{"type":"bitmap","libName":"timeline_bhitArea","x":-24.5,"y":-23,"r":0,"sx":1.8399658203125,"sy":1.8399658203125,"skewX":0,"skewY":0},"1":{"type":"bitmap","libName":"timeline_bBitmap 1fu","x":0,"y":4.75,"r":0,"sx":2,"sy":2,"skewX":0,"skewY":0}},"5":{"x":-452.5,"y":-257.95,"name":"a0","type":"sprite","r":0,"sx":1,"sy":1,"a":1,"skewX":0,"skewY":0,"0":{"type":"bitmap","libName":"timeline_bhitArea","x":-24.5,"y":-23,"r":0,"sx":1.8399658203125,"sy":1.8399658203125,"skewX":0,"skewY":0},"1":{"type":"bitmap","libName":"timeline_bBitmap 1fu","x":0,"y":4.75,"r":0,"sx":2,"sy":2,"skewX":0,"skewY":0}},"6":{"x":-426.15,"y":-245.95,"name":"progressBar","type":"sprite","r":0,"sx":0.5623931884765625,"sy":1,"a":1,"skewX":0,"skewY":0,"0":{"type":"bitmap","libName":"timeline_byellow","x":0,"y":0,"r":0,"sx":1,"sy":1,"skewX":0,"skewY":0}},"7":{"type":"bitmap","libName":"timeline_bBitmap 88","x":-434.8,"y":-245.25,"r":0,"sx":0.568206787109375,"sy":1,"skewX":0,"skewY":0}},"3":{"x":324.35,"y":293.65,"name":"bottle0","type":"sprite","r":0,"sx":1.47998046875,"sy":1.47998046875,"a":1,"skewX":0,"skewY":0,"0":{"x":31.95,"y":0,"name":"cover","type":"sprite","r":0,"sx":1,"sy":1,"a":1,"skewX":0,"skewY":0,"0":{"type":"bitmap","libName":"Bitmap 6","x":0,"y":0,"r":0,"sx":1,"sy":1,"skewX":0,"skewY":0}},"1":{"type":"bitmap","libName":"Bitmap 7","x":0,"y":40,"r":0,"sx":1,"sy":1,"skewX":0,"skewY":0}},"4":{"x":416.85,"y":567.45,"name":"bottle","type":"nbMovie","r":0,"sx":1.47998046875,"sy":1.47998046875,"a":1,"skewX":0,"skewY":0,"0":{"index":2,"0":{"type":"bitmap","libName":"a0.png","x":-62.5,"y":-185,"r":0,"sx":1,"sy":1,"skewX":0,"skewY":0},"1":{"type":"bitmap","libName":"b0","x":-62.05,"y":-43.15,"r":0,"sx":1,"sy":1,"skewX":0,"skewY":0}},"1":{"index":2,"0":{"type":"bitmap","libName":"a0.png","x":-62.5,"y":-185,"r":0,"sx":1,"sy":1,"skewX":0,"skewY":0},"1":{"type":"bitmap","libName":"Bitmap 506","x":-62.05,"y":-51.55,"r":0,"sx":1,"sy":1,"skewX":0,"skewY":0}},"2":{"index":2,"0":{"type":"bitmap","libName":"a1.png","x":-105.2,"y":-199.75,"r":0,"sx":1,"sy":1,"skewX":0,"skewY":0},"1":{"type":"bitmap","libName":"Bitmap 505","x":-62.05,"y":-64.1,"r":0,"sx":1,"sy":1,"skewX":0,"skewY":0}},"3":{"index":2,"0":{"type":"bitmap","libName":"a1.png","x":-105.2,"y":-199.75,"r":0,"sx":1,"sy":1,"skewX":0,"skewY":0},"1":{"type":"bitmap","libName":"Bitmap 504","x":-66.75,"y":-61.35,"r":0,"sx":1,"sy":1,"skewX":0,"skewY":0}},"4":{"index":2,"0":{"type":"bitmap","libName":"a2.png","x":-161.55,"y":-198.6,"r":0,"sx":1,"sy":1,"skewX":0,"skewY":0},"1":{"type":"bitmap","libName":"Bitmap 503","x":-66.75,"y":-66.9,"r":0,"sx":1,"sy":1,"skewX":0,"skewY":0}},"5":{"index":2,"0":{"type":"bitmap","libName":"a2.png","x":-161.55,"y":-198.6,"r":0,"sx":1,"sy":1,"skewX":0,"skewY":0},"1":{"type":"bitmap","libName":"Bitmap 502","x":-147.7,"y":-93.5,"r":0,"sx":1,"sy":1,"skewX":0,"skewY":0}},"6":{"index":2,"0":{"type":"bitmap","libName":"a1.png","x":-105.2,"y":-199.75,"r":0,"sx":1,"sy":1,"skewX":0,"skewY":0},"1":{"type":"bitmap","libName":"Bitmap 501","x":-147.7,"y":-94.9,"r":0,"sx":1,"sy":1,"skewX":0,"skewY":0}},"7":{"index":2,"0":{"type":"bitmap","libName":"a1.png","x":-105.2,"y":-199.75,"r":0,"sx":1,"sy":1,"skewX":0,"skewY":0},"1":{"type":"bitmap","libName":"Bitmap 500","x":-66.75,"y":-73.05,"r":0,"sx":1,"sy":1,"skewX":0,"skewY":0}},"8":{"index":2,"0":{"type":"bitmap","libName":"a2.png","x":-161.55,"y":-198.6,"r":0,"sx":1,"sy":1,"skewX":0,"skewY":0},"1":{"type":"bitmap","libName":"Bitmap 499","x":-66.75,"y":-83.25,"r":0,"sx":1,"sy":1,"skewX":0,"skewY":0}},"9":{"index":2,"0":{"type":"bitmap","libName":"a2.png","x":-161.55,"y":-198.6,"r":0,"sx":1,"sy":1,"skewX":0,"skewY":0},"1":{"type":"bitmap","libName":"Bitmap 498","x":-147.7,"y":-99.75,"r":0,"sx":1,"sy":1,"skewX":0,"skewY":0}},"10":{"index":2,"0":{"type":"bitmap","libName":"a1.png","x":-105.2,"y":-199.75,"r":0,"sx":1,"sy":1,"skewX":0,"skewY":0},"1":{"type":"bitmap","libName":"Bitmap 497","x":-147.7,"y":-76.1,"r":0,"sx":1,"sy":1,"skewX":0,"skewY":0}},"11":{"index":2,"0":{"type":"bitmap","libName":"a1.png","x":-105.2,"y":-199.75,"r":0,"sx":1,"sy":1,"skewX":0,"skewY":0},"1":{"type":"bitmap","libName":"Bitmap 496","x":-66.75,"y":-98.9,"r":0,"sx":1,"sy":1,"skewX":0,"skewY":0}},"12":{"index":2,"0":{"type":"bitmap","libName":"a2.png","x":-161.55,"y":-198.6,"r":0,"sx":1,"sy":1,"skewX":0,"skewY":0},"1":{"type":"bitmap","libName":"Bitmap 495","x":-66.75,"y":-100.05,"r":0,"sx":1,"sy":1,"skewX":0,"skewY":0}},"13":{"index":2,"0":{"type":"bitmap","libName":"a2.png","x":-161.55,"y":-198.6,"r":0,"sx":1,"sy":1,"skewX":0,"skewY":0},"1":{"type":"bitmap","libName":"Bitmap 494","x":-147.7,"y":-79.7,"r":0,"sx":1,"sy":1,"skewX":0,"skewY":0}},"14":{"index":2,"0":{"type":"bitmap","libName":"a1.png","x":-105.2,"y":-199.75,"r":0,"sx":1,"sy":1,"skewX":0,"skewY":0},"1":{"type":"bitmap","libName":"Bitmap 493","x":-147.7,"y":-82.55,"r":0,"sx":1,"sy":1,"skewX":0,"skewY":0}},"15":{"index":2,"0":{"type":"bitmap","libName":"a1.png","x":-105.2,"y":-199.75,"r":0,"sx":1,"sy":1,"skewX":0,"skewY":0},"1":{"type":"bitmap","libName":"Bitmap 492","x":-66.75,"y":-103.6,"r":0,"sx":1,"sy":1,"skewX":0,"skewY":0}},"16":{"index":2,"0":{"type":"bitmap","libName":"a2.png","x":-161.55,"y":-198.6,"r":0,"sx":1,"sy":1,"skewX":0,"skewY":0},"1":{"type":"bitmap","libName":"Bitmap 491","x":-66.75,"y":-68.2,"r":0,"sx":1,"sy":1,"skewX":0,"skewY":0}},"17":{"index":2,"0":{"type":"bitmap","libName":"a2.png","x":-161.55,"y":-198.6,"r":0,"sx":1,"sy":1,"skewX":0,"skewY":0},"1":{"type":"bitmap","libName":"Bitmap 490","x":-147.7,"y":-94.9,"r":0,"sx":1,"sy":1,"skewX":0,"skewY":0}},"18":{"index":2,"0":{"type":"bitmap","libName":"a1.png","x":-105.2,"y":-199.75,"r":0,"sx":1,"sy":1,"skewX":0,"skewY":0},"1":{"type":"bitmap","libName":"Bitmap 489","x":-147.7,"y":-97.1,"r":0,"sx":1,"sy":1,"skewX":0,"skewY":0}},"19":{"index":2,"0":{"type":"bitmap","libName":"a1.png","x":-105.2,"y":-199.75,"r":0,"sx":1,"sy":1,"skewX":0,"skewY":0},"1":{"type":"bitmap","libName":"Bitmap 488","x":-66.75,"y":-83.25,"r":0,"sx":1,"sy":1,"skewX":0,"skewY":0}},"20":{"index":2,"0":{"type":"bitmap","libName":"a2.png","x":-161.55,"y":-198.6,"r":0,"sx":1,"sy":1,"skewX":0,"skewY":0},"1":{"type":"bitmap","libName":"Bitmap 487","x":-66.75,"y":-87.85,"r":0,"sx":1,"sy":1,"skewX":0,"skewY":0}},"21":{"index":2,"0":{"type":"bitmap","libName":"a2.png","x":-161.55,"y":-198.6,"r":0,"sx":1,"sy":1,"skewX":0,"skewY":0},"1":{"type":"bitmap","libName":"Bitmap 486","x":-147.7,"y":-79.7,"r":0,"sx":1,"sy":1,"skewX":0,"skewY":0}},"22":{"index":2,"0":{"type":"bitmap","libName":"a1.png","x":-105.2,"y":-199.75,"r":0,"sx":1,"sy":1,"skewX":0,"skewY":0},"1":{"type":"bitmap","libName":"Bitmap 485","x":-147.7,"y":-76.1,"r":0,"sx":1,"sy":1,"skewX":0,"skewY":0}},"23":{"index":2,"0":{"type":"bitmap","libName":"a1.png","x":-105.2,"y":-199.75,"r":0,"sx":1,"sy":1,"skewX":0,"skewY":0},"1":{"type":"bitmap","libName":"Bitmap 484","x":-66.75,"y":-100.05,"r":0,"sx":1,"sy":1,"skewX":0,"skewY":0}},"24":{"index":2,"0":{"type":"bitmap","libName":"a2.png","x":-161.55,"y":-198.6,"r":0,"sx":1,"sy":1,"skewX":0,"skewY":0},"1":{"type":"bitmap","libName":"Bitmap 483","x":-66.75,"y":-101.55,"r":0,"sx":1,"sy":1,"skewX":0,"skewY":0}},"25":{"index":2,"0":{"type":"bitmap","libName":"a2.png","x":-161.55,"y":-198.6,"r":0,"sx":1,"sy":1,"skewX":0,"skewY":0},"1":{"type":"bitmap","libName":"Bitmap 482","x":-147.7,"y":-82.55,"r":0,"sx":1,"sy":1,"skewX":0,"skewY":0}},"26":{"index":2,"0":{"type":"bitmap","libName":"a0.png","x":-62.5,"y":-185,"r":0,"sx":1,"sy":1,"skewX":0,"skewY":0},"1":{"type":"bitmap","libName":"Bitmap 481","x":-147.7,"y":-92,"r":0,"sx":1,"sy":1,"skewX":0,"skewY":0}},"27":{"index":2,"0":{"type":"bitmap","libName":"a0.png","x":-62.5,"y":-185,"r":0,"sx":1,"sy":1,"skewX":0,"skewY":0},"1":{"type":"bitmap","libName":"Bitmap 480","x":-62.05,"y":-78,"r":0,"sx":1,"sy":1,"skewX":0,"skewY":0}},"28":{"index":2,"0":{"type":"bitmap","libName":"a0.png","x":-62.5,"y":-185,"r":0,"sx":1,"sy":1,"skewX":0,"skewY":0},"1":{"type":"bitmap","libName":"Bitmap 479","x":-62.05,"y":-79.3,"r":0,"sx":1,"sy":1,"skewX":0,"skewY":0}},"29":{"index":2,"0":{"type":"bitmap","libName":"a0.png","x":-62.5,"y":-185,"r":0,"sx":1,"sy":1,"skewX":0,"skewY":0},"1":{"type":"bitmap","libName":"Bitmap 478","x":-62.05,"y":-77.3,"r":0,"sx":1,"sy":1,"skewX":0,"skewY":0}},"30":{"index":2,"0":{"type":"bitmap","libName":"a0.png","x":-62.5,"y":-185,"r":0,"sx":1,"sy":1,"skewX":0,"skewY":0},"1":{"type":"bitmap","libName":"Bitmap 477","x":-62.05,"y":-76.45,"r":0,"sx":1,"sy":1,"skewX":0,"skewY":0}},"31":{"index":2,"0":{"type":"bitmap","libName":"a0.png","x":-62.5,"y":-185,"r":0,"sx":1,"sy":1,"skewX":0,"skewY":0},"1":{"type":"bitmap","libName":"Bitmap 476","x":-62.05,"y":-43.05,"r":0,"sx":1,"sy":1,"skewX":0,"skewY":0}},"32":{"index":2,"0":{"type":"bitmap","libName":"a0.png","x":-62.5,"y":-185,"r":0,"sx":1,"sy":1,"skewX":0,"skewY":0},"1":{"type":"bitmap","libName":"Bitmap 475","x":-62.05,"y":-43.05,"r":0,"sx":1,"sy":1,"skewX":0,"skewY":0}},"33":{"index":2,"0":{"type":"bitmap","libName":"a0.png","x":-62.5,"y":-185,"r":0,"sx":1,"sy":1,"skewX":0,"skewY":0},"1":{"type":"bitmap","libName":"Bitmap 474","x":-62.05,"y":-43.7,"r":0,"sx":1,"sy":1,"skewX":0,"skewY":0}},"34":{"index":2,"0":{"type":"bitmap","libName":"a0.png","x":-62.5,"y":-185,"r":0,"sx":1,"sy":1,"skewX":0,"skewY":0},"1":{"type":"bitmap","libName":"Bitmap 473","x":-62.05,"y":-43.7,"r":0,"sx":1,"sy":1,"skewX":0,"skewY":0}},"35":{"index":2,"0":{"type":"bitmap","libName":"a0.png","x":-62.5,"y":-185,"r":0,"sx":1,"sy":1,"skewX":0,"skewY":0},"1":{"type":"bitmap","libName":"Bitmap 472","x":-62.05,"y":-44.55,"r":0,"sx":1,"sy":1,"skewX":0,"skewY":0}},"36":{"index":2,"0":{"type":"bitmap","libName":"a0.png","x":-62.5,"y":-185,"r":0,"sx":1,"sy":1,"skewX":0,"skewY":0},"1":{"type":"bitmap","libName":"Bitmap 471","x":-62.05,"y":-44.55,"r":0,"sx":1,"sy":1,"skewX":0,"skewY":0}},"37":{"index":2,"0":{"type":"bitmap","libName":"a0.png","x":-62.5,"y":-185,"r":0,"sx":1,"sy":1,"skewX":0,"skewY":0},"1":{"type":"bitmap","libName":"Bitmap 470","x":-62.05,"y":-45.25,"r":0,"sx":1,"sy":1,"skewX":0,"skewY":0}},"38":{"index":2,"0":{"type":"bitmap","libName":"a0.png","x":-62.5,"y":-185,"r":0,"sx":1,"sy":1,"skewX":0,"skewY":0},"1":{"type":"bitmap","libName":"Bitmap 469","x":-62.05,"y":-45.25,"r":0,"sx":1,"sy":1,"skewX":0,"skewY":0}},"39":{"index":2,"0":{"type":"bitmap","libName":"a0.png","x":-62.5,"y":-185,"r":0,"sx":1,"sy":1,"skewX":0,"skewY":0},"1":{"type":"bitmap","libName":"Bitmap 468","x":-62.05,"y":-43.15,"r":0,"sx":1,"sy":1,"skewX":0,"skewY":0}},"40":{"index":2,"0":{"type":"bitmap","libName":"a0.png","x":-62.5,"y":-185,"r":0,"sx":1,"sy":1,"skewX":0,"skewY":0},"1":{"type":"bitmap","libName":"Bitmap 467","x":-62.05,"y":-43.15,"r":0,"sx":1,"sy":1,"skewX":0,"skewY":0}},"41":{"index":2,"0":{"type":"bitmap","libName":"a0.png","x":-62.5,"y":-185,"r":0,"sx":1,"sy":1,"skewX":0,"skewY":0},"1":{"type":"bitmap","libName":"Bitmap 466","x":-62.05,"y":-43.8,"r":0,"sx":1,"sy":1,"skewX":0,"skewY":0}},"42":{"index":2,"0":{"type":"bitmap","libName":"a0.png","x":-62.5,"y":-185,"r":0,"sx":1,"sy":1,"skewX":0,"skewY":0},"1":{"type":"bitmap","libName":"Bitmap 465","x":-62.05,"y":-43.15,"r":0,"sx":1,"sy":1,"skewX":0,"skewY":0}},"43":{"index":2,"0":{"type":"bitmap","libName":"a0.png","x":-62.5,"y":-185,"r":0,"sx":1,"sy":1,"skewX":0,"skewY":0},"1":{"type":"bitmap","libName":"Bitmap 464","x":-62.05,"y":-43.8,"r":0,"sx":1,"sy":1,"skewX":0,"skewY":0}},"44":{"index":2,"0":{"type":"bitmap","libName":"a0.png","x":-62.5,"y":-185,"r":0,"sx":1,"sy":1,"skewX":0,"skewY":0},"1":{"type":"bitmap","libName":"Bitmap 463","x":-62.05,"y":-43.8,"r":0,"sx":1,"sy":1,"skewX":0,"skewY":0}},"45":{"index":2,"0":{"type":"bitmap","libName":"a0.png","x":-62.5,"y":-185,"r":0,"sx":1,"sy":1,"skewX":0,"skewY":0},"1":{"type":"bitmap","libName":"Bitmap 462","x":-62.05,"y":-44.35,"r":0,"sx":1,"sy":1,"skewX":0,"skewY":0}},"46":{"index":2,"0":{"type":"bitmap","libName":"a0.png","x":-62.5,"y":-185,"r":0,"sx":1,"sy":1,"skewX":0,"skewY":0},"1":{"type":"bitmap","libName":"Bitmap 461","x":-62.05,"y":-44.35,"r":0,"sx":1,"sy":1,"skewX":0,"skewY":0}},"47":{"index":2,"0":{"type":"bitmap","libName":"a0.png","x":-62.5,"y":-185,"r":0,"sx":1,"sy":1,"skewX":0,"skewY":0},"1":{"type":"bitmap","libName":"Bitmap 460","x":-62.05,"y":-45.15,"r":0,"sx":1,"sy":1,"skewX":0,"skewY":0}},"48":{"index":2,"0":{"type":"bitmap","libName":"a0.png","x":-62.5,"y":-185,"r":0,"sx":1,"sy":1,"skewX":0,"skewY":0},"1":{"type":"bitmap","libName":"Bitmap 459","x":-62.05,"y":-45.15,"r":0,"sx":1,"sy":1,"skewX":0,"skewY":0}},"49":{"index":2,"0":{"type":"bitmap","libName":"a0.png","x":-62.5,"y":-185,"r":0,"sx":1,"sy":1,"skewX":0,"skewY":0},"1":{"type":"bitmap","libName":"Bitmap 458","x":-62.05,"y":-43.05,"r":0,"sx":1,"sy":1,"skewX":0,"skewY":0}},"50":{"index":2,"0":{"type":"bitmap","libName":"a0.png","x":-62.5,"y":-185,"r":0,"sx":1,"sy":1,"skewX":0,"skewY":0},"1":{"type":"bitmap","libName":"Bitmap 457","x":-62.05,"y":-43.05,"r":0,"sx":1,"sy":1,"skewX":0,"skewY":0}},"51":{"index":2,"0":{"type":"bitmap","libName":"a0.png","x":-62.5,"y":-185,"r":0,"sx":1,"sy":1,"skewX":0,"skewY":0},"1":{"type":"bitmap","libName":"Bitmap 456","x":-62.05,"y":-43.7,"r":0,"sx":1,"sy":1,"skewX":0,"skewY":0}},"52":{"index":2,"0":{"type":"bitmap","libName":"a0.png","x":-62.5,"y":-185,"r":0,"sx":1,"sy":1,"skewX":0,"skewY":0},"1":{"type":"bitmap","libName":"Bitmap 455","x":-62.05,"y":-43.7,"r":0,"sx":1,"sy":1,"skewX":0,"skewY":0}},"53":{"index":2,"0":{"type":"bitmap","libName":"a0.png","x":-62.5,"y":-185,"r":0,"sx":1,"sy":1,"skewX":0,"skewY":0},"1":{"type":"bitmap","libName":"Bitmap 454","x":-62.05,"y":-44.55,"r":0,"sx":1,"sy":1,"skewX":0,"skewY":0}},"54":{"index":2,"0":{"type":"bitmap","libName":"a0.png","x":-62.5,"y":-185,"r":0,"sx":1,"sy":1,"skewX":0,"skewY":0},"1":{"type":"bitmap","libName":"Bitmap 453","x":-62.05,"y":-44.55,"r":0,"sx":1,"sy":1,"skewX":0,"skewY":0}},"55":{"index":2,"0":{"type":"bitmap","libName":"a0.png","x":-62.5,"y":-185,"r":0,"sx":1,"sy":1,"skewX":0,"skewY":0},"1":{"type":"bitmap","libName":"Bitmap 452","x":-62.05,"y":-45.25,"r":0,"sx":1,"sy":1,"skewX":0,"skewY":0}},"56":{"index":2,"0":{"type":"bitmap","libName":"a0.png","x":-62.5,"y":-185,"r":0,"sx":1,"sy":1,"skewX":0,"skewY":0},"1":{"type":"bitmap","libName":"b0","x":-62.05,"y":-43.15,"r":0,"sx":1,"sy":1,"skewX":0,"skewY":0}}},"5":{"x":213.4,"y":546.6,"name":"stone","type":"nbMovie","r":0,"sx":2.13616943359375,"sy":2.13616943359375,"a":1,"skewX":0,"skewY":0,"0":{"index":1,"0":{"x":104.8,"y":116,"name":"a0","type":"sprite","r":0,"sx":1,"sy":1,"a":1,"skewX":0,"skewY":0,"0":{"type":"bitmap","libName":"圆润1_qc.png","x":-24.8,"y":-16.15,"r":0,"sx":0.476959228515625,"sy":0.476959228515625,"skewX":0,"skewY":0},"1":{"type":"bitmap","libName":"圆润2_qc.png","x":15.1,"y":-4,"r":2.2595837942758674,"sx":0.3977508544921875,"sy":0.3977508544921875,"skewX":2.2595837942758674,"skewY":2.2595837942758674}}},"1":{"index":1,"0":{"x":104.8,"y":116,"name":"a1","type":"sprite","r":0,"sx":1,"sy":1,"a":1,"skewX":0,"skewY":0,"0":{"type":"bitmap","libName":"圆润1_qc.png","x":-24.8,"y":-16.15,"r":0,"sx":0.476959228515625,"sy":0.476959228515625,"skewX":0,"skewY":0},"1":{"type":"bitmap","libName":"圆润2_qc.png","x":15.1,"y":-4,"r":2.2595837942758674,"sx":0.3977508544921875,"sy":0.3977508544921875,"skewX":2.2595837942758674,"skewY":2.2595837942758674}}},"2":{"index":1,"0":{"x":141.3,"y":95,"name":"a2","type":"sprite","r":-1.8107711094608465,"sx":0.9999847412109375,"sy":0.9999847412109375,"a":1,"skewX":-1.8107711094608465,"skewY":-1.8107711094608465,"0":{"type":"bitmap","libName":"圆润1_qc.png","x":-24.8,"y":-16.15,"r":0,"sx":0.476959228515625,"sy":0.476959228515625,"skewX":0,"skewY":0},"1":{"type":"bitmap","libName":"圆润2_qc.png","x":15.1,"y":-4,"r":2.2595837942758674,"sx":0.3977508544921875,"sy":0.3977508544921875,"skewX":2.2595837942758674,"skewY":2.2595837942758674}}},"3":{"index":1,"0":{"x":141.3,"y":95,"name":"a3","type":"sprite","r":-1.8107711094608465,"sx":0.9999847412109375,"sy":0.9999847412109375,"a":1,"skewX":-1.8107711094608465,"skewY":-1.8107711094608465,"0":{"type":"bitmap","libName":"圆润1_qc.png","x":-24.8,"y":-16.15,"r":0,"sx":0.476959228515625,"sy":0.476959228515625,"skewX":0,"skewY":0},"1":{"type":"bitmap","libName":"圆润2_qc.png","x":15.1,"y":-4,"r":2.2595837942758674,"sx":0.3977508544921875,"sy":0.3977508544921875,"skewX":2.2595837942758674,"skewY":2.2595837942758674}}},"4":{"index":1,"0":{"x":53,"y":96.9,"name":"a4","type":"sprite","r":2.081422312091201,"sx":0.9999847412109375,"sy":0.9999847412109375,"a":1,"skewX":2.081422312091201,"skewY":2.081422312091201,"0":{"type":"bitmap","libName":"圆润1_qc.png","x":-24.8,"y":-16.15,"r":0,"sx":0.476959228515625,"sy":0.476959228515625,"skewX":0,"skewY":0},"1":{"type":"bitmap","libName":"圆润2_qc.png","x":15.1,"y":-4,"r":2.2595837942758674,"sx":0.3977508544921875,"sy":0.3977508544921875,"skewX":2.2595837942758674,"skewY":2.2595837942758674}}},"5":{"index":1,"0":{"x":53,"y":96.9,"name":"a5","type":"sprite","r":2.081422312091201,"sx":0.9999847412109375,"sy":0.9999847412109375,"a":1,"skewX":2.081422312091201,"skewY":2.081422312091201,"0":{"type":"bitmap","libName":"圆润1_qc.png","x":-24.8,"y":-16.15,"r":0,"sx":0.476959228515625,"sy":0.476959228515625,"skewX":0,"skewY":0},"1":{"type":"bitmap","libName":"圆润2_qc.png","x":15.1,"y":-4,"r":2.2595837942758674,"sx":0.3977508544921875,"sy":0.3977508544921875,"skewX":2.2595837942758674,"skewY":2.2595837942758674}}},"6":{"index":1,"0":{"x":151,"y":99.5,"name":"a6","type":"sprite","r":-0.7030321835195866,"sx":0.9999847412109375,"sy":0.9999847412109375,"a":1,"skewX":-0.7030321835195866,"skewY":-0.7030321835195866,"0":{"type":"bitmap","libName":"圆润1_qc.png","x":-24.8,"y":-16.15,"r":0,"sx":0.476959228515625,"sy":0.476959228515625,"skewX":0,"skewY":0},"1":{"type":"bitmap","libName":"圆润2_qc.png","x":15.1,"y":-4,"r":2.2595837942758674,"sx":0.3977508544921875,"sy":0.3977508544921875,"skewX":2.2595837942758674,"skewY":2.2595837942758674}}},"7":{"index":1,"0":{"x":151,"y":99.5,"name":"a7","type":"sprite","r":-0.7030321835195866,"sx":0.9999847412109375,"sy":0.9999847412109375,"a":1,"skewX":-0.7030321835195866,"skewY":-0.7030321835195866,"0":{"type":"bitmap","libName":"圆润1_qc.png","x":-24.8,"y":-16.15,"r":0,"sx":0.476959228515625,"sy":0.476959228515625,"skewX":0,"skewY":0},"1":{"type":"bitmap","libName":"圆润2_qc.png","x":15.1,"y":-4,"r":2.2595837942758674,"sx":0.3977508544921875,"sy":0.3977508544921875,"skewX":2.2595837942758674,"skewY":2.2595837942758674}}},"8":{"index":1,"0":{"x":62.75,"y":78.85,"name":"a8","type":"sprite","r":1.9468301453402317,"sx":0.999969482421875,"sy":0.999969482421875,"a":1,"skewX":1.9468301453402317,"skewY":1.9468301453402317,"0":{"type":"bitmap","libName":"圆润1_qc.png","x":-24.8,"y":-16.15,"r":0,"sx":0.476959228515625,"sy":0.476959228515625,"skewX":0,"skewY":0},"1":{"type":"bitmap","libName":"圆润2_qc.png","x":15.1,"y":-4,"r":2.2595837942758674,"sx":0.3977508544921875,"sy":0.3977508544921875,"skewX":2.2595837942758674,"skewY":2.2595837942758674}}},"9":{"index":1,"0":{"x":62.75,"y":78.85,"name":"a9","type":"sprite","r":1.9468301453402317,"sx":0.999969482421875,"sy":0.999969482421875,"a":1,"skewX":1.9468301453402317,"skewY":1.9468301453402317,"0":{"type":"bitmap","libName":"圆润1_qc.png","x":-24.8,"y":-16.15,"r":0,"sx":0.476959228515625,"sy":0.476959228515625,"skewX":0,"skewY":0},"1":{"type":"bitmap","libName":"圆润2_qc.png","x":15.1,"y":-4,"r":2.2595837942758674,"sx":0.3977508544921875,"sy":0.3977508544921875,"skewX":2.2595837942758674,"skewY":2.2595837942758674}}},"10":{"index":1,"0":{"x":133,"y":87.5,"name":"a10","type":"sprite","r":1.1431336684089581,"sx":0.9999847412109375,"sy":0.9999847412109375,"a":1,"skewX":1.1431336684089581,"skewY":1.1431336684089581,"0":{"type":"bitmap","libName":"圆润1_qc.png","x":-24.8,"y":-16.15,"r":0,"sx":0.476959228515625,"sy":0.476959228515625,"skewX":0,"skewY":0},"1":{"type":"bitmap","libName":"圆润2_qc.png","x":15.1,"y":-4,"r":2.2595837942758674,"sx":0.3977508544921875,"sy":0.3977508544921875,"skewX":2.2595837942758674,"skewY":2.2595837942758674}}},"11":{"index":1,"0":{"x":133,"y":87.5,"name":"a11","type":"sprite","r":1.1431336684089581,"sx":0.9999847412109375,"sy":0.9999847412109375,"a":1,"skewX":1.1431336684089581,"skewY":1.1431336684089581,"0":{"type":"bitmap","libName":"圆润1_qc.png","x":-24.8,"y":-16.15,"r":0,"sx":0.476959228515625,"sy":0.476959228515625,"skewX":0,"skewY":0},"1":{"type":"bitmap","libName":"圆润2_qc.png","x":15.1,"y":-4,"r":2.2595837942758674,"sx":0.3977508544921875,"sy":0.3977508544921875,"skewX":2.2595837942758674,"skewY":2.2595837942758674}}},"12":{"index":1,"0":{"x":44.75,"y":112,"name":"a12","type":"sprite","r":-0.026833744827529395,"sx":1,"sy":1,"a":1,"skewX":-0.026833744827529395,"skewY":-0.026833744827529395,"0":{"type":"bitmap","libName":"圆润1_qc.png","x":-24.8,"y":-16.15,"r":0,"sx":0.476959228515625,"sy":0.476959228515625,"skewX":0,"skewY":0},"1":{"type":"bitmap","libName":"圆润2_qc.png","x":15.1,"y":-4,"r":2.2595837942758674,"sx":0.3977508544921875,"sy":0.3977508544921875,"skewX":2.2595837942758674,"skewY":2.2595837942758674}}},"13":{"index":1,"0":{"x":44.75,"y":112,"name":"a13","type":"sprite","r":-0.026833744827529395,"sx":1,"sy":1,"a":1,"skewX":-0.026833744827529395,"skewY":-0.026833744827529395,"0":{"type":"bitmap","libName":"圆润1_qc.png","x":-24.8,"y":-16.15,"r":0,"sx":0.476959228515625,"sy":0.476959228515625,"skewX":0,"skewY":0},"1":{"type":"bitmap","libName":"圆润2_qc.png","x":15.1,"y":-4,"r":2.2595837942758674,"sx":0.3977508544921875,"sy":0.3977508544921875,"skewX":2.2595837942758674,"skewY":2.2595837942758674}}},"14":{"index":1,"0":{"x":138.3,"y":101,"name":"a14","type":"sprite","r":2.059927406300954,"sx":0.999969482421875,"sy":0.999969482421875,"a":1,"skewX":2.059927406300954,"skewY":2.059927406300954,"0":{"type":"bitmap","libName":"圆润1_qc.png","x":-24.8,"y":-16.15,"r":0,"sx":0.476959228515625,"sy":0.476959228515625,"skewX":0,"skewY":0},"1":{"type":"bitmap","libName":"圆润2_qc.png","x":15.1,"y":-4,"r":2.2595837942758674,"sx":0.3977508544921875,"sy":0.3977508544921875,"skewX":2.2595837942758674,"skewY":2.2595837942758674}}},"15":{"index":1,"0":{"x":138.3,"y":101,"name":"a15","type":"sprite","r":2.059927406300954,"sx":0.999969482421875,"sy":0.999969482421875,"a":1,"skewX":2.059927406300954,"skewY":2.059927406300954,"0":{"type":"bitmap","libName":"圆润1_qc.png","x":-24.8,"y":-16.15,"r":0,"sx":0.476959228515625,"sy":0.476959228515625,"skewX":0,"skewY":0},"1":{"type":"bitmap","libName":"圆润2_qc.png","x":15.1,"y":-4,"r":2.2595837942758674,"sx":0.3977508544921875,"sy":0.3977508544921875,"skewX":2.2595837942758674,"skewY":2.2595837942758674}}},"16":{"index":1,"0":{"x":44.75,"y":105.8,"name":"a16","type":"sprite","r":2.1290119355064814,"sx":1.1522979736328125,"sy":1.073455810546875,"a":1,"skewX":2.1290119355064814,"skewY":2.1290119355064814,"0":{"type":"bitmap","libName":"圆润1_qc.png","x":-24.8,"y":-16.15,"r":0,"sx":0.476959228515625,"sy":0.476959228515625,"skewX":0,"skewY":0},"1":{"type":"bitmap","libName":"圆润2_qc.png","x":15.1,"y":-4,"r":2.2595837942758674,"sx":0.3977508544921875,"sy":0.3977508544921875,"skewX":2.2595837942758674,"skewY":2.2595837942758674}}},"17":{"index":1,"0":{"x":44.75,"y":105.8,"name":"a17","type":"sprite","r":2.1290119355064814,"sx":1.1522979736328125,"sy":1.073455810546875,"a":1,"skewX":2.1290119355064814,"skewY":2.1290119355064814,"0":{"type":"bitmap","libName":"圆润1_qc.png","x":-24.8,"y":-16.15,"r":0,"sx":0.476959228515625,"sy":0.476959228515625,"skewX":0,"skewY":0},"1":{"type":"bitmap","libName":"圆润2_qc.png","x":15.1,"y":-4,"r":2.2595837942758674,"sx":0.3977508544921875,"sy":0.3977508544921875,"skewX":2.2595837942758674,"skewY":2.2595837942758674}}},"18":{"index":1,"0":{"x":151.8,"y":107,"name":"a18","type":"sprite","r":-0.11320724951374231,"sx":0.9999847412109375,"sy":0.9999847412109375,"a":1,"skewX":-0.11320724951374231,"skewY":-0.11320724951374231,"0":{"type":"bitmap","libName":"圆润1_qc.png","x":-24.8,"y":-16.15,"r":0,"sx":0.476959228515625,"sy":0.476959228515625,"skewX":0,"skewY":0},"1":{"type":"bitmap","libName":"圆润2_qc.png","x":15.1,"y":-4,"r":2.2595837942758674,"sx":0.3977508544921875,"sy":0.3977508544921875,"skewX":2.2595837942758674,"skewY":2.2595837942758674}}},"19":{"index":1,"0":{"x":151.8,"y":107,"name":"a19","type":"sprite","r":-0.11320724951374231,"sx":0.9999847412109375,"sy":0.9999847412109375,"a":1,"skewX":-0.11320724951374231,"skewY":-0.11320724951374231,"0":{"type":"bitmap","libName":"圆润1_qc.png","x":-24.8,"y":-16.15,"r":0,"sx":0.476959228515625,"sy":0.476959228515625,"skewX":0,"skewY":0},"1":{"type":"bitmap","libName":"圆润2_qc.png","x":15.1,"y":-4,"r":2.2595837942758674,"sx":0.3977508544921875,"sy":0.3977508544921875,"skewX":2.2595837942758674,"skewY":2.2595837942758674}}},"20":{"index":1,"0":{"x":55.25,"y":80.3,"name":"a20","type":"sprite","r":3.0760586507495593,"sx":1,"sy":1,"a":1,"skewX":3.0760586507495593,"skewY":3.0760586507495593,"0":{"type":"bitmap","libName":"圆润1_qc.png","x":-24.8,"y":-16.15,"r":0,"sx":0.476959228515625,"sy":0.476959228515625,"skewX":0,"skewY":0},"1":{"type":"bitmap","libName":"圆润2_qc.png","x":15.1,"y":-4,"r":2.2595837942758674,"sx":0.3977508544921875,"sy":0.3977508544921875,"skewX":2.2595837942758674,"skewY":2.2595837942758674}}},"21":{"index":1,"0":{"x":55.25,"y":80.3,"name":"a21","type":"sprite","r":3.0760586507495593,"sx":1,"sy":1,"a":1,"skewX":3.0760586507495593,"skewY":3.0760586507495593,"0":{"type":"bitmap","libName":"圆润1_qc.png","x":-24.8,"y":-16.15,"r":0,"sx":0.476959228515625,"sy":0.476959228515625,"skewX":0,"skewY":0},"1":{"type":"bitmap","libName":"圆润2_qc.png","x":15.1,"y":-4,"r":2.2595837942758674,"sx":0.3977508544921875,"sy":0.3977508544921875,"skewX":2.2595837942758674,"skewY":2.2595837942758674}}},"22":{"index":1,"0":{"x":152.15,"y":115.6,"name":"a22","type":"sprite","r":0.3618306478197247,"sx":0.9999847412109375,"sy":0.9999847412109375,"a":1,"skewX":0.3618306478197247,"skewY":0.3618306478197247,"0":{"type":"bitmap","libName":"圆润1_qc.png","x":-24.8,"y":-16.15,"r":0,"sx":0.476959228515625,"sy":0.476959228515625,"skewX":0,"skewY":0},"1":{"type":"bitmap","libName":"圆润2_qc.png","x":15.1,"y":-4,"r":2.2595837942758674,"sx":0.3977508544921875,"sy":0.3977508544921875,"skewX":2.2595837942758674,"skewY":2.2595837942758674}}},"23":{"index":1,"0":{"x":152.15,"y":115.6,"name":"a23","type":"sprite","r":0.3618306478197247,"sx":0.9999847412109375,"sy":0.9999847412109375,"a":1,"skewX":0.3618306478197247,"skewY":0.3618306478197247,"0":{"type":"bitmap","libName":"圆润1_qc.png","x":-24.8,"y":-16.15,"r":0,"sx":0.476959228515625,"sy":0.476959228515625,"skewX":0,"skewY":0},"1":{"type":"bitmap","libName":"圆润2_qc.png","x":15.1,"y":-4,"r":2.2595837942758674,"sx":0.3977508544921875,"sy":0.3977508544921875,"skewX":2.2595837942758674,"skewY":2.2595837942758674}}},"24":{"index":1,"0":{"x":50,"y":108.9,"name":"a24","type":"sprite","r":-0.03573615971944628,"sx":0.9999847412109375,"sy":0.9999847412109375,"a":1,"skewX":-0.03573615971944628,"skewY":-0.03573615971944628,"0":{"type":"bitmap","libName":"圆润1_qc.png","x":-24.8,"y":-16.15,"r":0,"sx":0.476959228515625,"sy":0.476959228515625,"skewX":0,"skewY":0},"1":{"type":"bitmap","libName":"圆润2_qc.png","x":15.1,"y":-4,"r":2.2595837942758674,"sx":0.3977508544921875,"sy":0.3977508544921875,"skewX":2.2595837942758674,"skewY":2.2595837942758674}}},"25":{"index":1,"0":{"x":50,"y":108.9,"name":"a25","type":"sprite","r":-0.03573615971944628,"sx":0.9999847412109375,"sy":0.9999847412109375,"a":1,"skewX":-0.03573615971944628,"skewY":-0.03573615971944628,"0":{"type":"bitmap","libName":"圆润1_qc.png","x":-24.8,"y":-16.15,"r":0,"sx":0.476959228515625,"sy":0.476959228515625,"skewX":0,"skewY":0},"1":{"type":"bitmap","libName":"圆润2_qc.png","x":15.1,"y":-4,"r":2.2595837942758674,"sx":0.3977508544921875,"sy":0.3977508544921875,"skewX":2.2595837942758674,"skewY":2.2595837942758674}}},"26":{"index":1,"0":{"x":76.55,"y":86,"name":"a26","type":"sprite","r":0,"sx":1,"sy":1,"a":1,"skewX":0,"skewY":0,"0":{"type":"bitmap","libName":"圆润1_qc.png","x":-19.4,"y":13.25,"r":-1.238513451269601,"sx":0.4769439697265625,"sy":0.4769439697265625,"skewX":-1.238513451269601,"skewY":-1.238513451269601},"1":{"type":"bitmap","libName":"圆润2_qc.png","x":5.1,"y":-20.5,"r":1.0211004367265843,"sx":0.3977508544921875,"sy":0.3977508544921875,"skewX":1.0211004367265843,"skewY":1.0211004367265843}}},"27":{"index":1,"0":{"x":90.65,"y":89.5,"name":"a27","type":"sprite","r":2.7044954807261403,"sx":0.998748779296875,"sy":0.998748779296875,"a":1,"skewX":2.7044954807261403,"skewY":2.7044954807261403,"0":{"type":"bitmap","libName":"圆润1_qc.png","x":-19.4,"y":13.25,"r":-1.238513451269601,"sx":0.4769439697265625,"sy":0.4769439697265625,"skewX":-1.238513451269601,"skewY":-1.238513451269601},"1":{"type":"bitmap","libName":"圆润2_qc.png","x":5.1,"y":-20.5,"r":1.0211004367265843,"sx":0.3977508544921875,"sy":0.3977508544921875,"skewX":1.0211004367265843,"skewY":1.0211004367265843}}},"28":{"index":1,"0":{"x":101.55,"y":92.2,"name":"a28","type":"sprite","r":-1.4781060703191247,"sx":0.99969482421875,"sy":0.99969482421875,"a":1,"skewX":-1.4781060703191247,"skewY":-1.4781060703191247,"0":{"type":"bitmap","libName":"圆润1_qc.png","x":-19.4,"y":13.25,"r":-1.238513451269601,"sx":0.4769439697265625,"sy":0.4769439697265625,"skewX":-1.238513451269601,"skewY":-1.238513451269601},"1":{"type":"bitmap","libName":"圆润2_qc.png","x":5.1,"y":-20.5,"r":1.0211004367265843,"sx":0.3977508544921875,"sy":0.3977508544921875,"skewX":1.0211004367265843,"skewY":1.0211004367265843}}},"29":{"index":1,"0":{"x":109.4,"y":94.15,"name":"a29","type":"sprite","r":0.026543992900928775,"sx":0.9999237060546875,"sy":0.9999237060546875,"a":1,"skewX":0.026543992900928775,"skewY":0.026543992900928775,"0":{"type":"bitmap","libName":"圆润1_qc.png","x":-19.4,"y":13.25,"r":-1.238513451269601,"sx":0.4769439697265625,"sy":0.4769439697265625,"skewX":-1.238513451269601,"skewY":-1.238513451269601},"1":{"type":"bitmap","libName":"圆润2_qc.png","x":5.1,"y":-20.5,"r":1.0211004367265843,"sx":0.3977508544921875,"sy":0.3977508544921875,"skewX":1.0211004367265843,"skewY":1.0211004367265843}}},"30":{"index":1,"0":{"x":114.1,"y":95.3,"name":"a30","type":"sprite","r":0.9281462609867854,"sx":0.9984283447265625,"sy":0.9984283447265625,"a":1,"skewX":0.9281462609867854,"skewY":0.9281462609867854,"0":{"type":"bitmap","libName":"圆润1_qc.png","x":-19.4,"y":13.25,"r":-1.238513451269601,"sx":0.4769439697265625,"sy":0.4769439697265625,"skewX":-1.238513451269601,"skewY":-1.238513451269601},"1":{"type":"bitmap","libName":"圆润2_qc.png","x":5.1,"y":-20.5,"r":1.0211004367265843,"sx":0.3977508544921875,"sy":0.3977508544921875,"skewX":1.0211004367265843,"skewY":1.0211004367265843}}},"31":{"index":1,"0":{"x":115.65,"y":95.7,"name":"a31","type":"sprite","r":1.2295694910646788,"sx":0.9999847412109375,"sy":0.9999847412109375,"a":1,"skewX":1.2295694910646788,"skewY":1.2295694910646788,"0":{"type":"bitmap","libName":"圆润1_qc.png","x":-19.4,"y":13.25,"r":-1.238513451269601,"sx":0.4769439697265625,"sy":0.4769439697265625,"skewX":-1.238513451269601,"skewY":-1.238513451269601},"1":{"type":"bitmap","libName":"圆润2_qc.png","x":5.1,"y":-20.5,"r":1.0211004367265843,"sx":0.3977508544921875,"sy":0.3977508544921875,"skewX":1.0211004367265843,"skewY":1.0211004367265843}}},"32":{"index":1,"0":{"x":111.65,"y":98.45,"name":"a32","type":"sprite","r":-3.080085882949977,"sx":0.999786376953125,"sy":0.999786376953125,"a":1,"skewX":-3.080085882949977,"skewY":-3.080085882949977,"0":{"type":"bitmap","libName":"圆润1_qc.png","x":-19.4,"y":13.25,"r":-1.238513451269601,"sx":0.4769439697265625,"sy":0.4769439697265625,"skewX":-1.238513451269601,"skewY":-1.238513451269601},"1":{"type":"bitmap","libName":"圆润2_qc.png","x":5.1,"y":-20.5,"r":1.0211004367265843,"sx":0.3977508544921875,"sy":0.3977508544921875,"skewX":1.0211004367265843,"skewY":1.0211004367265843}}},"33":{"index":1,"0":{"x":108.1,"y":100.85,"name":"a33","type":"sprite","r":-1.4088660125059365,"sx":0.999481201171875,"sy":0.999481201171875,"a":1,"skewX":-1.4088660125059365,"skewY":-1.4088660125059365,"0":{"type":"bitmap","libName":"圆润1_qc.png","x":-19.4,"y":13.25,"r":-1.238513451269601,"sx":0.4769439697265625,"sy":0.4769439697265625,"skewX":-1.238513451269601,"skewY":-1.238513451269601},"1":{"type":"bitmap","libName":"圆润2_qc.png","x":5.1,"y":-20.5,"r":1.0211004367265843,"sx":0.3977508544921875,"sy":0.3977508544921875,"skewX":1.0211004367265843,"skewY":1.0211004367265843}}},"34":{"index":1,"0":{"x":105.25,"y":102.8,"name":"a34","type":"sprite","r":-0.03959108539733597,"sx":0.9998626708984375,"sy":0.9998626708984375,"a":1,"skewX":-0.03959108539733597,"skewY":-0.03959108539733597,"0":{"type":"bitmap","libName":"圆润1_qc.png","x":-19.4,"y":13.25,"r":-1.238513451269601,"sx":0.4769439697265625,"sy":0.4769439697265625,"skewX":-1.238513451269601,"skewY":-1.238513451269601},"1":{"type":"bitmap","libName":"圆润2_qc.png","x":5.1,"y":-20.5,"r":1.0211004367265843,"sx":0.3977508544921875,"sy":0.3977508544921875,"skewX":1.0211004367265843,"skewY":1.0211004367265843}}},"35":{"index":1,"0":{"x":103.05,"y":104.2,"name":"a35","type":"sprite","r":1.0238229863089723,"sx":0.9985198974609375,"sy":0.9985198974609375,"a":1,"skewX":1.0238229863089723,"skewY":1.0238229863089723,"0":{"type":"bitmap","libName":"圆润1_qc.png","x":-19.4,"y":13.25,"r":-1.238513451269601,"sx":0.4769439697265625,"sy":0.4769439697265625,"skewX":-1.238513451269601,"skewY":-1.238513451269601},"1":{"type":"bitmap","libName":"圆润2_qc.png","x":5.1,"y":-20.5,"r":1.0211004367265843,"sx":0.3977508544921875,"sy":0.3977508544921875,"skewX":1.0211004367265843,"skewY":1.0211004367265843}}},"36":{"index":1,"0":{"x":101.5,"y":105.3,"name":"a36","type":"sprite","r":1.7808619462064939,"sx":0.99932861328125,"sy":0.99932861328125,"a":1,"skewX":1.7808619462064939,"skewY":1.7808619462064939,"0":{"type":"bitmap","libName":"圆润1_qc.png","x":-19.4,"y":13.25,"r":-1.238513451269601,"sx":0.4769439697265625,"sy":0.4769439697265625,"skewX":-1.238513451269601,"skewY":-1.238513451269601},"1":{"type":"bitmap","libName":"圆润2_qc.png","x":5.1,"y":-20.5,"r":1.0211004367265843,"sx":0.3977508544921875,"sy":0.3977508544921875,"skewX":1.0211004367265843,"skewY":1.0211004367265843}}},"37":{"index":1,"0":{"x":100.55,"y":105.95,"name":"a37","type":"sprite","r":2.236248910488484,"sx":0.9983978271484375,"sy":0.9983978271484375,"a":1,"skewX":2.236248910488484,"skewY":2.236248910488484,"0":{"type":"bitmap","libName":"圆润1_qc.png","x":-19.4,"y":13.25,"r":-1.238513451269601,"sx":0.4769439697265625,"sy":0.4769439697265625,"skewX":-1.238513451269601,"skewY":-1.238513451269601},"1":{"type":"bitmap","libName":"圆润2_qc.png","x":5.1,"y":-20.5,"r":1.0211004367265843,"sx":0.3977508544921875,"sy":0.3977508544921875,"skewX":1.0211004367265843,"skewY":1.0211004367265843}}},"38":{"index":1,"0":{"x":100.25,"y":106.2,"name":"a38","type":"sprite","r":2.389821426328448,"sx":0.9999847412109375,"sy":0.9999847412109375,"a":1,"skewX":2.389821426328448,"skewY":2.389821426328448,"0":{"type":"bitmap","libName":"圆润1_qc.png","x":-19.4,"y":13.25,"r":-1.238513451269601,"sx":0.4769439697265625,"sy":0.4769439697265625,"skewX":-1.238513451269601,"skewY":-1.238513451269601},"1":{"type":"bitmap","libName":"圆润2_qc.png","x":5.1,"y":-20.5,"r":1.0211004367265843,"sx":0.3977508544921875,"sy":0.3977508544921875,"skewX":1.0211004367265843,"skewY":1.0211004367265843}}},"39":{"index":1,"0":{"x":102.5,"y":107.8,"name":"a39","type":"sprite","r":2.257634360357929,"sx":0.99835205078125,"sy":0.99835205078125,"a":1,"skewX":2.257634360357929,"skewY":2.257634360357929,"0":{"type":"bitmap","libName":"圆润1_qc.png","x":-19.4,"y":13.25,"r":-1.238513451269601,"sx":0.4769439697265625,"sy":0.4769439697265625,"skewX":-1.238513451269601,"skewY":-1.238513451269601},"1":{"type":"bitmap","libName":"圆润2_qc.png","x":5.1,"y":-20.5,"r":1.0211004367265843,"sx":0.3977508544921875,"sy":0.3977508544921875,"skewX":1.0211004367265843,"skewY":1.0211004367265843}}},"40":{"index":1,"0":{"x":104.65,"y":109.25,"name":"a40","type":"sprite","r":2.135048789065473,"sx":0.99847412109375,"sy":0.99847412109375,"a":1,"skewX":2.135048789065473,"skewY":2.135048789065473,"0":{"type":"bitmap","libName":"圆润1_qc.png","x":-19.4,"y":13.25,"r":-1.238513451269601,"sx":0.4769439697265625,"sy":0.4769439697265625,"skewX":-1.238513451269601,"skewY":-1.238513451269601},"1":{"type":"bitmap","libName":"圆润2_qc.png","x":5.1,"y":-20.5,"r":1.0211004367265843,"sx":0.3977508544921875,"sy":0.3977508544921875,"skewX":1.0211004367265843,"skewY":1.0211004367265843}}},"41":{"index":1,"0":{"x":106.55,"y":110.65,"name":"a41","type":"sprite","r":2.0215198296920494,"sx":0.9986572265625,"sy":0.9986572265625,"a":1,"skewX":2.0215198296920494,"skewY":2.0215198296920494,"0":{"type":"bitmap","libName":"圆润1_qc.png","x":-19.4,"y":13.25,"r":-1.238513451269601,"sx":0.4769439697265625,"sy":0.4769439697265625,"skewX":-1.238513451269601,"skewY":-1.238513451269601},"1":{"type":"bitmap","libName":"圆润2_qc.png","x":5.1,"y":-20.5,"r":1.0211004367265843,"sx":0.3977508544921875,"sy":0.3977508544921875,"skewX":1.0211004367265843,"skewY":1.0211004367265843}}},"42":{"index":1,"0":{"x":108.35,"y":111.9,"name":"a42","type":"sprite","r":1.9202912124453742,"sx":0.9989166259765625,"sy":0.9989166259765625,"a":1,"skewX":1.9202912124453742,"skewY":1.9202912124453742,"0":{"type":"bitmap","libName":"圆润1_qc.png","x":-19.4,"y":13.25,"r":-1.238513451269601,"sx":0.4769439697265625,"sy":0.4769439697265625,"skewX":-1.238513451269601,"skewY":-1.238513451269601},"1":{"type":"bitmap","libName":"圆润2_qc.png","x":5.1,"y":-20.5,"r":1.0211004367265843,"sx":0.3977508544921875,"sy":0.3977508544921875,"skewX":1.0211004367265843,"skewY":1.0211004367265843}}},"43":{"index":1,"0":{"x":109.9,"y":113.1,"name":"a43","type":"sprite","r":1.8248877274510298,"sx":0.999176025390625,"sy":0.999176025390625,"a":1,"skewX":1.8248877274510298,"skewY":1.8248877274510298,"0":{"type":"bitmap","libName":"圆润1_qc.png","x":-19.4,"y":13.25,"r":-1.238513451269601,"sx":0.4769439697265625,"sy":0.4769439697265625,"skewX":-1.238513451269601,"skewY":-1.238513451269601},"1":{"type":"bitmap","libName":"圆润2_qc.png","x":5.1,"y":-20.5,"r":1.0211004367265843,"sx":0.3977508544921875,"sy":0.3977508544921875,"skewX":1.0211004367265843,"skewY":1.0211004367265843}}},"44":{"index":1,"0":{"x":111.35,"y":114.05,"name":"a44","type":"sprite","r":1.7418381141213448,"sx":0.9994049072265625,"sy":0.9994049072265625,"a":1,"skewX":1.7418381141213448,"skewY":1.7418381141213448,"0":{"type":"bitmap","libName":"圆润1_qc.png","x":-19.4,"y":13.25,"r":-1.238513451269601,"sx":0.4769439697265625,"sy":0.4769439697265625,"skewX":-1.238513451269601,"skewY":-1.238513451269601},"1":{"type":"bitmap","libName":"圆润2_qc.png","x":5.1,"y":-20.5,"r":1.0211004367265843,"sx":0.3977508544921875,"sy":0.3977508544921875,"skewX":1.0211004367265843,"skewY":1.0211004367265843}}},"45":{"index":1,"0":{"x":112.65,"y":114.9,"name":"a45","type":"sprite","r":1.66778119684453,"sx":0.999664306640625,"sy":0.999664306640625,"a":1,"skewX":1.66778119684453,"skewY":1.66778119684453,"0":{"type":"bitmap","libName":"圆润1_qc.png","x":-19.4,"y":13.25,"r":-1.238513451269601,"sx":0.4769439697265625,"sy":0.4769439697265625,"skewX":-1.238513451269601,"skewY":-1.238513451269601},"1":{"type":"bitmap","libName":"圆润2_qc.png","x":5.1,"y":-20.5,"r":1.0211004367265843,"sx":0.3977508544921875,"sy":0.3977508544921875,"skewX":1.0211004367265843,"skewY":1.0211004367265843}}},"46":{"index":1,"0":{"x":113.7,"y":115.7,"name":"a46","type":"sprite","r":1.6060600417369628,"sx":0.999847412109375,"sy":0.999847412109375,"a":1,"skewX":1.6060600417369628,"skewY":1.6060600417369628,"0":{"type":"bitmap","libName":"圆润1_qc.png","x":-19.4,"y":13.25,"r":-1.238513451269601,"sx":0.4769439697265625,"sy":0.4769439697265625,"skewX":-1.238513451269601,"skewY":-1.238513451269601},"1":{"type":"bitmap","libName":"圆润2_qc.png","x":5.1,"y":-20.5,"r":1.0211004367265843,"sx":0.3977508544921875,"sy":0.3977508544921875,"skewX":1.0211004367265843,"skewY":1.0211004367265843}}},"47":{"index":1,"0":{"x":114.65,"y":116.35,"name":"a47","type":"sprite","r":1.5533267889923037,"sx":0.999908447265625,"sy":0.999908447265625,"a":1,"skewX":1.5533267889923037,"skewY":1.5533267889923037,"0":{"type":"bitmap","libName":"圆润1_qc.png","x":-19.4,"y":13.25,"r":-1.238513451269601,"sx":0.4769439697265625,"sy":0.4769439697265625,"skewX":-1.238513451269601,"skewY":-1.238513451269601},"1":{"type":"bitmap","libName":"圆润2_qc.png","x":5.1,"y":-20.5,"r":1.0211004367265843,"sx":0.3977508544921875,"sy":0.3977508544921875,"skewX":1.0211004367265843,"skewY":1.0211004367265843}}},"48":{"index":1,"0":{"x":115.4,"y":116.95,"name":"a48","type":"sprite","r":1.509578242817245,"sx":0.999786376953125,"sy":0.999786376953125,"a":1,"skewX":1.509578242817245,"skewY":1.509578242817245,"0":{"type":"bitmap","libName":"圆润1_qc.png","x":-19.4,"y":13.25,"r":-1.238513451269601,"sx":0.4769439697265625,"sy":0.4769439697265625,"skewX":-1.238513451269601,"skewY":-1.238513451269601},"1":{"type":"bitmap","libName":"圆润2_qc.png","x":5.1,"y":-20.5,"r":1.0211004367265843,"sx":0.3977508544921875,"sy":0.3977508544921875,"skewX":1.0211004367265843,"skewY":1.0211004367265843}}},"49":{"index":1,"0":{"x":115.95,"y":117.25,"name":"a49","type":"sprite","r":1.4780908903009111,"sx":0.999664306640625,"sy":0.999664306640625,"a":1,"skewX":1.4780908903009111,"skewY":1.4780908903009111,"0":{"type":"bitmap","libName":"圆润1_qc.png","x":-19.4,"y":13.25,"r":-1.238513451269601,"sx":0.4769439697265625,"sy":0.4769439697265625,"skewX":-1.238513451269601,"skewY":-1.238513451269601},"1":{"type":"bitmap","libName":"圆润2_qc.png","x":5.1,"y":-20.5,"r":1.0211004367265843,"sx":0.3977508544921875,"sy":0.3977508544921875,"skewX":1.0211004367265843,"skewY":1.0211004367265843}}},"50":{"index":1,"0":{"x":116.4,"y":117.55,"name":"a50","type":"sprite","r":1.4523349267665369,"sx":0.9995880126953125,"sy":0.9995880126953125,"a":1,"skewX":1.4523349267665369,"skewY":1.4523349267665369,"0":{"type":"bitmap","libName":"圆润1_qc.png","x":-19.4,"y":13.25,"r":-1.238513451269601,"sx":0.4769439697265625,"sy":0.4769439697265625,"skewX":-1.238513451269601,"skewY":-1.238513451269601},"1":{"type":"bitmap","libName":"圆润2_qc.png","x":5.1,"y":-20.5,"r":1.0211004367265843,"sx":0.3977508544921875,"sy":0.3977508544921875,"skewX":1.0211004367265843,"skewY":1.0211004367265843}}},"51":{"index":1,"0":{"x":116.65,"y":117.8,"name":"a51","type":"sprite","r":1.4388164547571858,"sx":0.9995574951171875,"sy":0.9995574951171875,"a":1,"skewX":1.4388164547571858,"skewY":1.4388164547571858,"0":{"type":"bitmap","libName":"圆润1_qc.png","x":-19.4,"y":13.25,"r":-1.238513451269601,"sx":0.4769439697265625,"sy":0.4769439697265625,"skewX":-1.238513451269601,"skewY":-1.238513451269601},"1":{"type":"bitmap","libName":"圆润2_qc.png","x":5.1,"y":-20.5,"r":1.0211004367265843,"sx":0.3977508544921875,"sy":0.3977508544921875,"skewX":1.0211004367265843,"skewY":1.0211004367265843}}},"52":{"index":1,"0":{"x":116.75,"y":117.85,"name":"a52","type":"sprite","r":1.4309526726903998,"sx":0.999969482421875,"sy":0.999969482421875,"a":1,"skewX":1.4309526726903998,"skewY":1.4309526726903998,"0":{"type":"bitmap","libName":"圆润1_qc.png","x":-19.4,"y":13.25,"r":-1.238513451269601,"sx":0.4769439697265625,"sy":0.4769439697265625,"skewX":-1.238513451269601,"skewY":-1.238513451269601},"1":{"type":"bitmap","libName":"圆润2_qc.png","x":5.1,"y":-20.5,"r":1.0211004367265843,"sx":0.3977508544921875,"sy":0.3977508544921875,"skewX":1.0211004367265843,"skewY":1.0211004367265843}}},"53":{"index":1,"0":{"x":116.75,"y":117.85,"name":"a53","type":"sprite","r":1.4309526726903998,"sx":0.999969482421875,"sy":0.999969482421875,"a":1,"skewX":1.4309526726903998,"skewY":1.4309526726903998,"0":{"type":"bitmap","libName":"圆润1_qc.png","x":-19.4,"y":13.25,"r":-1.238513451269601,"sx":0.4769439697265625,"sy":0.4769439697265625,"skewX":-1.238513451269601,"skewY":-1.238513451269601},"1":{"type":"bitmap","libName":"圆润2_qc.png","x":5.1,"y":-20.5,"r":1.0211004367265843,"sx":0.3977508544921875,"sy":0.3977508544921875,"skewX":1.0211004367265843,"skewY":1.0211004367265843}}},"54":{"index":1,"0":{"x":116.75,"y":117.85,"name":"a54","type":"sprite","r":1.4309526726903998,"sx":0.999969482421875,"sy":0.999969482421875,"a":1,"skewX":1.4309526726903998,"skewY":1.4309526726903998,"0":{"type":"bitmap","libName":"圆润1_qc.png","x":-19.4,"y":13.25,"r":-1.238513451269601,"sx":0.4769439697265625,"sy":0.4769439697265625,"skewX":-1.238513451269601,"skewY":-1.238513451269601},"1":{"type":"bitmap","libName":"圆润2_qc.png","x":5.1,"y":-20.5,"r":1.0211004367265843,"sx":0.3977508544921875,"sy":0.3977508544921875,"skewX":1.0211004367265843,"skewY":1.0211004367265843}}}},"6":{"x":897.5,"y":697.9,"name":"st","type":"sprite","r":0,"sx":2.13116455078125,"sy":2.13116455078125,"a":1,"skewX":0,"skewY":0,"0":{"type":"bitmap","libName":"Bitmap 449","x":0,"y":0,"r":0,"sx":1,"sy":1,"skewX":0,"skewY":0}},"7":{"x":320.45,"y":189.75,"name":"ref","type":"sprite","r":0,"sx":1,"sy":1,"a":1,"skewX":0,"skewY":0,"0":{"type":"shape","path":[255,0,0,2,0,193.65,2,671.05,193.65,2,671.05,0,2,0,0,2,0,0,1,0,65280,33]}}},"3":{"x":0,"y":0,"name":"step0","type":"sprite","r":0,"sx":1,"sy":1,"a":1,"skewX":0,"skewY":0,"0":{"x":1007.25,"y":1112.7,"w":122.6,"h":56.75,"name":"txt4","type":"text","r":0,"txt":"火柴","a":"center","f":"40px 'Microsoft YaHei'","c":"#FFFFFF"},"1":{"x":158,"y":1112.7,"w":118.3,"h":56.75,"name":"txt2","type":"text","r":0,"txt":"镊子","a":"center","f":"40px 'Microsoft YaHei'","c":"#FFFFFF"},"2":{"x":897.2,"y":711.1,"w":164.1,"h":56.75,"name":"txt1","type":"text","r":0,"txt":"酒精灯","a":"center","f":"40px 'Microsoft YaHei'","c":"#FFFFFF"},"3":{"x":346.05,"y":711.1,"w":111.25,"h":56.75,"name":"txt0","type":"text","r":0,"txt":"清水","a":"center","f":"40px 'Microsoft YaHei'","c":"#FFFFFF"},"4":{"x":568.45,"y":1112.7,"w":108.9,"h":56.75,"name":"txt3","type":"text","r":0,"txt":"石头","a":"center","f":"40px 'Microsoft YaHei'","c":"#FFFFFF"},"5":{"x":249.5,"y":335.35,"name":"cup","type":"nbMovie","r":0,"sx":1.329986572265625,"sy":1.329986572265625,"a":1,"skewX":0,"skewY":0,"0":{"index":1,"0":{"type":"bitmap","libName":"装有清水的烧杯_qc.png","x":0,"y":0,"r":0,"sx":1,"sy":1,"skewX":0,"skewY":0}},"1":{"index":2,"0":{"type":"bitmap","libName":"装有清水的烧杯_qc.png","x":0,"y":0,"r":0,"sx":1,"sy":1,"skewX":0,"skewY":0},"1":{"type":"bitmap","libName":"Bitmap 139","x":83.05,"y":131.2,"r":0,"sx":1,"sy":1,"skewX":0,"skewY":0}},"2":{"index":2,"0":{"type":"bitmap","libName":"装有清水的烧杯_qc.png","x":0,"y":0,"r":0,"sx":1,"sy":1,"skewX":0,"skewY":0},"1":{"type":"bitmap","libName":"Bitmap 138","x":82.75,"y":138.25,"r":0,"sx":1,"sy":1,"skewX":0,"skewY":0}},"3":{"index":2,"0":{"type":"bitmap","libName":"装有清水的烧杯_qc.png","x":0,"y":0,"r":0,"sx":1,"sy":1,"skewX":0,"skewY":0},"1":{"type":"bitmap","libName":"Bitmap 137","x":83.4,"y":145.75,"r":0,"sx":1,"sy":1,"skewX":0,"skewY":0}},"4":{"index":2,"0":{"type":"bitmap","libName":"装有清水的烧杯_qc.png","x":0,"y":0,"r":0,"sx":1,"sy":1,"skewX":0,"skewY":0},"1":{"type":"bitmap","libName":"Bitmap 136","x":83.4,"y":138.25,"r":0,"sx":1,"sy":1,"skewX":0,"skewY":0}},"5":{"index":2,"0":{"type":"bitmap","libName":"装有清水的烧杯_qc.png","x":0,"y":0,"r":0,"sx":1,"sy":1,"skewX":0,"skewY":0},"1":{"type":"bitmap","libName":"Bitmap 135","x":82.65,"y":145.75,"r":0,"sx":1,"sy":1,"skewX":0,"skewY":0}},"6":{"index":2,"0":{"type":"bitmap","libName":"装有清水的烧杯_qc.png","x":0,"y":0,"r":0,"sx":1,"sy":1,"skewX":0,"skewY":0},"1":{"type":"bitmap","libName":"Bitmap 134","x":82.65,"y":153.05,"r":0,"sx":1,"sy":1,"skewX":0,"skewY":0}},"7":{"index":2,"0":{"type":"bitmap","libName":"装有清水的烧杯_qc.png","x":0,"y":0,"r":0,"sx":1,"sy":1,"skewX":0,"skewY":0},"1":{"type":"bitmap","libName":"Bitmap 133","x":82.65,"y":160.05,"r":0,"sx":1,"sy":1,"skewX":0,"skewY":0}},"8":{"index":2,"0":{"type":"bitmap","libName":"装有清水的烧杯_qc.png","x":0,"y":0,"r":0,"sx":1,"sy":1,"skewX":0,"skewY":0},"1":{"type":"bitmap","libName":"Bitmap 132","x":82.65,"y":158.6,"r":0,"sx":1,"sy":1,"skewX":0,"skewY":0}},"9":{"index":2,"0":{"type":"bitmap","libName":"装有清水的烧杯_qc.png","x":0,"y":0,"r":0,"sx":1,"sy":1,"skewX":0,"skewY":0},"1":{"type":"bitmap","libName":"Bitmap 131","x":83.05,"y":163.45,"r":0,"sx":1,"sy":1,"skewX":0,"skewY":0}},"10":{"index":2,"0":{"type":"bitmap","libName":"装有清水的烧杯_qc.png","x":0,"y":0,"r":0,"sx":1,"sy":1,"skewX":0,"skewY":0},"1":{"type":"bitmap","libName":"Bitmap 130","x":83.75,"y":131.2,"r":0,"sx":1,"sy":1,"skewX":0,"skewY":0}},"11":{"index":2,"0":{"type":"bitmap","libName":"装有清水的烧杯_qc.png","x":0,"y":0,"r":0,"sx":1,"sy":1,"skewX":0,"skewY":0},"1":{"type":"bitmap","libName":"Bitmap 129","x":83.3,"y":138.25,"r":0,"sx":1,"sy":1,"skewX":0,"skewY":0}},"12":{"index":2,"0":{"type":"bitmap","libName":"装有清水的烧杯_qc.png","x":0,"y":0,"r":0,"sx":1,"sy":1,"skewX":0,"skewY":0},"1":{"type":"bitmap","libName":"Bitmap 128","x":82.8,"y":131.2,"r":0,"sx":1,"sy":1,"skewX":0,"skewY":0}},"13":{"index":2,"0":{"type":"bitmap","libName":"装有清水的烧杯_qc.png","x":0,"y":0,"r":0,"sx":1,"sy":1,"skewX":0,"skewY":0},"1":{"type":"bitmap","libName":"Bitmap 127","x":82.5,"y":138.25,"r":0,"sx":1,"sy":1,"skewX":0,"skewY":0}},"14":{"index":2,"0":{"type":"bitmap","libName":"装有清水的烧杯_qc.png","x":0,"y":0,"r":0,"sx":1,"sy":1,"skewX":0,"skewY":0},"1":{"type":"bitmap","libName":"Bitmap 126","x":82.4,"y":145.75,"r":0,"sx":1,"sy":1,"skewX":0,"skewY":0}},"15":{"index":2,"0":{"type":"bitmap","libName":"装有清水的烧杯_qc.png","x":0,"y":0,"r":0,"sx":1,"sy":1,"skewX":0,"skewY":0},"1":{"type":"bitmap","libName":"Bitmap 125","x":82.45,"y":153.05,"r":0,"sx":1,"sy":1,"skewX":0,"skewY":0}},"16":{"index":2,"0":{"type":"bitmap","libName":"装有清水的烧杯_qc.png","x":0,"y":0,"r":0,"sx":1,"sy":1,"skewX":0,"skewY":0},"1":{"type":"bitmap","libName":"Bitmap 124","x":82.5,"y":160.05,"r":0,"sx":1,"sy":1,"skewX":0,"skewY":0}},"17":{"index":2,"0":{"type":"bitmap","libName":"装有清水的烧杯_qc.png","x":0,"y":0,"r":0,"sx":1,"sy":1,"skewX":0,"skewY":0},"1":{"type":"bitmap","libName":"Bitmap 123","x":82.75,"y":167.35,"r":0,"sx":1,"sy":1,"skewX":0,"skewY":0}},"18":{"index":2,"0":{"type":"bitmap","libName":"装有清水的烧杯_qc.png","x":0,"y":0,"r":0,"sx":1,"sy":1,"skewX":0,"skewY":0},"1":{"type":"bitmap","libName":"Bitmap 122","x":82.6,"y":173.1,"r":0,"sx":1,"sy":1,"skewX":0,"skewY":0}},"19":{"index":2,"0":{"type":"bitmap","libName":"装有清水的烧杯_qc.png","x":0,"y":0,"r":0,"sx":1,"sy":1,"skewX":0,"skewY":0},"1":{"type":"bitmap","libName":"Bitmap 121","x":82.6,"y":178.05,"r":0,"sx":1,"sy":1,"skewX":0,"skewY":0}},"20":{"index":2,"0":{"type":"bitmap","libName":"装有清水的烧杯_qc.png","x":0,"y":0,"r":0,"sx":1,"sy":1,"skewX":0,"skewY":0},"1":{"type":"bitmap","libName":"Bitmap 120","x":82.6,"y":183.05,"r":0,"sx":1,"sy":1,"skewX":0,"skewY":0}},"21":{"index":2,"0":{"type":"bitmap","libName":"装有清水的烧杯_qc.png","x":0,"y":0,"r":0,"sx":1,"sy":1,"skewX":0,"skewY":0},"1":{"type":"bitmap","libName":"Bitmap 119","x":82.6,"y":187.95,"r":0,"sx":1,"sy":1,"skewX":0,"skewY":0}},"22":{"index":2,"0":{"type":"bitmap","libName":"装有清水的烧杯_qc.png","x":0,"y":0,"r":0,"sx":1,"sy":1,"skewX":0,"skewY":0},"1":{"type":"bitmap","libName":"Bitmap 118","x":82.6,"y":192,"r":0,"sx":1,"sy":1,"skewX":0,"skewY":0}},"23":{"index":2,"0":{"type":"bitmap","libName":"装有清水的烧杯_qc.png","x":0,"y":0,"r":0,"sx":1,"sy":1,"skewX":0,"skewY":0},"1":{"type":"bitmap","libName":"Bitmap 117","x":82.6,"y":195.65,"r":0,"sx":1,"sy":1,"skewX":0,"skewY":0}},"24":{"index":2,"0":{"type":"bitmap","libName":"装有清水的烧杯_qc.png","x":0,"y":0,"r":0,"sx":1,"sy":1,"skewX":0,"skewY":0},"1":{"type":"bitmap","libName":"Bitmap 116","x":82.6,"y":199.1,"r":0,"sx":1,"sy":1,"skewX":0,"skewY":0}},"25":{"index":2,"0":{"type":"bitmap","libName":"装有清水的烧杯_qc.png","x":0,"y":0,"r":0,"sx":1,"sy":1,"skewX":0,"skewY":0},"1":{"type":"bitmap","libName":"Bitmap 115","x":82.6,"y":202.3,"r":0,"sx":1,"sy":1,"skewX":0,"skewY":0}},"26":{"index":2,"0":{"type":"bitmap","libName":"装有清水的烧杯_qc.png","x":0,"y":0,"r":0,"sx":1,"sy":1,"skewX":0,"skewY":0},"1":{"type":"bitmap","libName":"Bitmap 114","x":82.6,"y":205.1,"r":0,"sx":1,"sy":1,"skewX":0,"skewY":0}},"27":{"index":2,"0":{"type":"bitmap","libName":"装有清水的烧杯_qc.png","x":0,"y":0,"r":0,"sx":1,"sy":1,"skewX":0,"skewY":0},"1":{"type":"bitmap","libName":"Bitmap 113","x":82.6,"y":207.4,"r":0,"sx":1,"sy":1,"skewX":0,"skewY":0}},"28":{"index":2,"0":{"type":"bitmap","libName":"装有清水的烧杯_qc.png","x":0,"y":0,"r":0,"sx":1,"sy":1,"skewX":0,"skewY":0},"1":{"type":"bitmap","libName":"Bitmap 112","x":82.6,"y":209.15,"r":0,"sx":1,"sy":1,"skewX":0,"skewY":0}},"29":{"index":2,"0":{"type":"bitmap","libName":"装有清水的烧杯_qc.png","x":0,"y":0,"r":0,"sx":1,"sy":1,"skewX":0,"skewY":0},"1":{"type":"bitmap","libName":"Bitmap 111","x":82.6,"y":210.2,"r":0,"sx":1,"sy":1,"skewX":0,"skewY":0}},"30":{"index":2,"0":{"type":"bitmap","libName":"装有清水的烧杯_qc.png","x":0,"y":0,"r":0,"sx":1,"sy":1,"skewX":0,"skewY":0},"1":{"type":"bitmap","libName":"Bitmap 110","x":82.6,"y":210.7,"r":0,"sx":1,"sy":1,"skewX":0,"skewY":0}},"31":{"index":2,"0":{"type":"bitmap","libName":"装有清水的烧杯_qc.png","x":0,"y":0,"r":0,"sx":1,"sy":1,"skewX":0,"skewY":0},"1":{"type":"bitmap","libName":"Bitmap 194","x":82.6,"y":118.65,"r":0,"sx":1,"sy":1,"skewX":0,"skewY":0}},"32":{"index":2,"0":{"type":"bitmap","libName":"装有清水的烧杯_qc.png","x":0,"y":0,"r":0,"sx":1,"sy":1,"skewX":0,"skewY":0},"1":{"type":"bitmap","libName":"Bitmap 193","x":82.6,"y":125.8,"r":0,"sx":1,"sy":1,"skewX":0,"skewY":0}},"33":{"index":2,"0":{"type":"bitmap","libName":"装有清水的烧杯_qc.png","x":0,"y":0,"r":0,"sx":1,"sy":1,"skewX":0,"skewY":0},"1":{"type":"bitmap","libName":"Bitmap 192","x":82.6,"y":134.75,"r":0,"sx":1,"sy":1,"skewX":0,"skewY":0}},"34":{"index":2,"0":{"type":"bitmap","libName":"装有清水的烧杯_qc.png","x":0,"y":0,"r":0,"sx":1,"sy":1,"skewX":0,"skewY":0},"1":{"type":"bitmap","libName":"Bitmap 191","x":82.6,"y":145.65,"r":0,"sx":1,"sy":1,"skewX":0,"skewY":0}},"35":{"index":2,"0":{"type":"bitmap","libName":"装有清水的烧杯_qc.png","x":0,"y":0,"r":0,"sx":1,"sy":1,"skewX":0,"skewY":0},"1":{"type":"bitmap","libName":"Bitmap 190","x":82.6,"y":158.2,"r":0,"sx":1,"sy":1,"skewX":0,"skewY":0}},"36":{"index":2,"0":{"type":"bitmap","libName":"装有清水的烧杯_qc.png","x":0,"y":0,"r":0,"sx":1,"sy":1,"skewX":0,"skewY":0},"1":{"type":"bitmap","libName":"Bitmap 189","x":82.6,"y":166.95,"r":0,"sx":1,"sy":1,"skewX":0,"skewY":0}},"37":{"index":2,"0":{"type":"bitmap","libName":"装有清水的烧杯_qc.png","x":0,"y":0,"r":0,"sx":1,"sy":1,"skewX":0,"skewY":0},"1":{"type":"bitmap","libName":"Bitmap 188","x":82.6,"y":177.25,"r":0,"sx":1,"sy":1,"skewX":0,"skewY":0}},"38":{"index":2,"0":{"type":"bitmap","libName":"装有清水的烧杯_qc.png","x":0,"y":0,"r":0,"sx":1,"sy":1,"skewX":0,"skewY":0},"1":{"type":"bitmap","libName":"Bitmap 187","x":82.6,"y":189.05,"r":0,"sx":1,"sy":1,"skewX":0,"skewY":0}},"39":{"index":2,"0":{"type":"bitmap","libName":"装有清水的烧杯_qc.png","x":0,"y":0,"r":0,"sx":1,"sy":1,"skewX":0,"skewY":0},"1":{"type":"bitmap","libName":"Bitmap 186","x":82.6,"y":202.1,"r":0,"sx":1,"sy":1,"skewX":0,"skewY":0}},"40":{"index":2,"0":{"type":"bitmap","libName":"装有清水的烧杯_qc.png","x":0,"y":0,"r":0,"sx":1,"sy":1,"skewX":0,"skewY":0},"1":{"type":"bitmap","libName":"Bitmap 185","x":82.6,"y":118.9,"r":0,"sx":1,"sy":1,"skewX":0,"skewY":0}},"41":{"index":2,"0":{"type":"bitmap","libName":"装有清水的烧杯_qc.png","x":0,"y":0,"r":0,"sx":1,"sy":1,"skewX":0,"skewY":0},"1":{"type":"bitmap","libName":"Bitmap 184","x":82.6,"y":127.9,"r":0,"sx":1,"sy":1,"skewX":0,"skewY":0}},"42":{"index":2,"0":{"type":"bitmap","libName":"装有清水的烧杯_qc.png","x":0,"y":0,"r":0,"sx":1,"sy":1,"skewX":0,"skewY":0},"1":{"type":"bitmap","libName":"Bitmap 183","x":82.6,"y":137.1,"r":0,"sx":1,"sy":1,"skewX":0,"skewY":0}},"43":{"index":2,"0":{"type":"bitmap","libName":"装有清水的烧杯_qc.png","x":0,"y":0,"r":0,"sx":1,"sy":1,"skewX":0,"skewY":0},"1":{"type":"bitmap","libName":"Bitmap 182","x":82.6,"y":147,"r":0,"sx":1,"sy":1,"skewX":0,"skewY":0}},"44":{"index":2,"0":{"type":"bitmap","libName":"装有清水的烧杯_qc.png","x":0,"y":0,"r":0,"sx":1,"sy":1,"skewX":0,"skewY":0},"1":{"type":"bitmap","libName":"Bitmap 181","x":82.6,"y":157.15,"r":0,"sx":1,"sy":1,"skewX":0,"skewY":0}},"45":{"index":2,"0":{"type":"bitmap","libName":"装有清水的烧杯_qc.png","x":0,"y":0,"r":0,"sx":1,"sy":1,"skewX":0,"skewY":0},"1":{"type":"bitmap","libName":"Bitmap 180","x":82.6,"y":167.8,"r":0,"sx":1,"sy":1,"skewX":0,"skewY":0}},"46":{"index":2,"0":{"type":"bitmap","libName":"装有清水的烧杯_qc.png","x":0,"y":0,"r":0,"sx":1,"sy":1,"skewX":0,"skewY":0},"1":{"type":"bitmap","libName":"Bitmap 179","x":82.6,"y":178.85,"r":0,"sx":1,"sy":1,"skewX":0,"skewY":0}},"47":{"index":2,"0":{"type":"bitmap","libName":"装有清水的烧杯_qc.png","x":0,"y":0,"r":0,"sx":1,"sy":1,"skewX":0,"skewY":0},"1":{"type":"bitmap","libName":"Bitmap 178","x":82.6,"y":190.25,"r":0,"sx":1,"sy":1,"skewX":0,"skewY":0}},"48":{"index":2,"0":{"type":"bitmap","libName":"装有清水的烧杯_qc.png","x":0,"y":0,"r":0,"sx":1,"sy":1,"skewX":0,"skewY":0},"1":{"type":"bitmap","libName":"Bitmap 177","x":82.6,"y":201.15,"r":0,"sx":1,"sy":1,"skewX":0,"skewY":0}},"49":{"index":2,"0":{"type":"bitmap","libName":"装有清水的烧杯_qc.png","x":0,"y":0,"r":0,"sx":1,"sy":1,"skewX":0,"skewY":0},"1":{"type":"bitmap","libName":"Bitmap 176","x":82.6,"y":132.2,"r":0,"sx":1,"sy":1,"skewX":0,"skewY":0}},"50":{"index":2,"0":{"type":"bitmap","libName":"装有清水的烧杯_qc.png","x":0,"y":0,"r":0,"sx":1,"sy":1,"skewX":0,"skewY":0},"1":{"type":"bitmap","libName":"Bitmap 175","x":82.6,"y":140.5,"r":0,"sx":1,"sy":1,"skewX":0,"skewY":0}},"51":{"index":2,"0":{"type":"bitmap","libName":"装有清水的烧杯_qc.png","x":0,"y":0,"r":0,"sx":1,"sy":1,"skewX":0,"skewY":0},"1":{"type":"bitmap","libName":"Bitmap 174","x":82.6,"y":148.8,"r":0,"sx":1,"sy":1,"skewX":0,"skewY":0}},"52":{"index":2,"0":{"type":"bitmap","libName":"装有清水的烧杯_qc.png","x":0,"y":0,"r":0,"sx":1,"sy":1,"skewX":0,"skewY":0},"1":{"type":"bitmap","libName":"Bitmap 173","x":82.6,"y":157.15,"r":0,"sx":1,"sy":1,"skewX":0,"skewY":0}},"53":{"index":2,"0":{"type":"bitmap","libName":"装有清水的烧杯_qc.png","x":0,"y":0,"r":0,"sx":1,"sy":1,"skewX":0,"skewY":0},"1":{"type":"bitmap","libName":"Bitmap 172","x":82.6,"y":165.4,"r":0,"sx":1,"sy":1,"skewX":0,"skewY":0}},"54":{"index":2,"0":{"type":"bitmap","libName":"装有清水的烧杯_qc.png","x":0,"y":0,"r":0,"sx":1,"sy":1,"skewX":0,"skewY":0},"1":{"type":"bitmap","libName":"Bitmap 171","x":82.6,"y":173.95,"r":0,"sx":1,"sy":1,"skewX":0,"skewY":0}},"55":{"index":2,"0":{"type":"bitmap","libName":"装有清水的烧杯_qc.png","x":0,"y":0,"r":0,"sx":1,"sy":1,"skewX":0,"skewY":0},"1":{"type":"bitmap","libName":"Bitmap 170","x":82.6,"y":182.3,"r":0,"sx":1,"sy":1,"skewX":0,"skewY":0}},"56":{"index":2,"0":{"type":"bitmap","libName":"装有清水的烧杯_qc.png","x":0,"y":0,"r":0,"sx":1,"sy":1,"skewX":0,"skewY":0},"1":{"type":"bitmap","libName":"Bitmap 169","x":82.6,"y":190.85,"r":0,"sx":1,"sy":1,"skewX":0,"skewY":0}},"57":{"index":2,"0":{"type":"bitmap","libName":"装有清水的烧杯_qc.png","x":0,"y":0,"r":0,"sx":1,"sy":1,"skewX":0,"skewY":0},"1":{"type":"bitmap","libName":"Bitmap 168","x":82.6,"y":199.35,"r":0,"sx":1,"sy":1,"skewX":0,"skewY":0}}},"6":{"x":957.65,"y":444.45,"name":"spiritLamp","type":"sprite","r":0,"sx":1.329986572265625,"sy":1.329986572265625,"a":1,"skewX":0,"skewY":0,"0":{"x":-1,"y":-29.95,"name":"corver","type":"sprite","r":0,"sx":1,"sy":1,"a":1,"skewX":0,"skewY":0,"0":{"type":"bitmap","libName":"sprite_hat.png","x":-23.5,"y":0,"r":0,"sx":1,"sy":1,"skewX":0,"skewY":0},"1":{"type":"shape","path":[255,-14,-44.85,2,-14,5.15,2,36,5.15,2,36,-44.85,-7.2,-36.45,-14,-44.85,3,0,3750201,33]},"2":{"x":-57.8,"y":-29,"name":"","type":"sprite","r":0,"sx":2.33831787109375,"sy":2.259246826171875,"a":1,"skewX":0,"skewY":0,"0":{"type":"bitmap","libName":"sprite_hitArea","x":0,"y":0,"r":0,"sx":1,"sy":1,"skewX":0,"skewY":0}}},"1":{"x":-26,"y":-100.1,"name":"fireArea","type":"sprite","r":0,"sx":1,"sy":2.28125,"a":1,"skewX":0,"skewY":0,"0":{"type":"bitmap","libName":"sprite_hitArea","x":0,"y":0,"r":0,"sx":1,"sy":1,"skewX":0,"skewY":0}},"2":{"x":-26,"y":-22.6,"name":"head","type":"sprite","r":0,"sx":1,"sy":1.17108154296875,"a":1,"skewX":0,"skewY":0,"0":{"type":"bitmap","libName":"sprite_hitArea","x":0,"y":0,"r":0,"sx":1,"sy":1,"skewX":0,"skewY":0}},"3":{"x":-69.25,"y":-10.6,"name":"body","type":"sprite","r":0,"sx":1,"sy":1,"a":1,"skewX":0,"skewY":0,"0":{"type":"bitmap","libName":"sprite_cup.png","x":0,"y":0,"r":0,"sx":1,"sy":1,"skewX":0,"skewY":0}}},"7":{"x":978.1,"y":904.45,"name":"matches","type":"sprite","r":0,"sx":1.149658203125,"sy":1.149658203125,"a":1,"skewX":0,"skewY":0,"0":{"x":85.45,"y":71.9,"name":"match","type":"sprite","r":0,"sx":1,"sy":1,"a":1,"skewX":0,"skewY":0,"0":{"x":-15,"y":25.05,"name":"fireArea","type":"sprite","r":0,"sx":1,"sy":1,"a":1,"skewX":0,"skewY":0,"0":{"type":"bitmap","libName":"matches_hitArea","x":0,"y":0,"r":0,"sx":1,"sy":1,"skewX":0,"skewY":0}},"1":{"type":"bitmap","libName":"matches_hitArea","x":-15,"y":-21,"r":0,"sx":3.1609954833984375,"sy":1.9210052490234375,"skewX":0,"skewY":0},"2":{"type":"bitmap","libName":"matches_match.png","x":0,"y":0,"r":0,"sx":1,"sy":1,"skewX":0,"skewY":0}},"1":{"type":"bitmap","libName":"matches_fire","x":-26,"y":-24.7,"r":0,"sx":1,"sy":1,"skewX":0,"skewY":0}},"8":{"x":206.4,"y":1013.55,"name":"iron","type":"nbMovie","r":0,"sx":1.329986572265625,"sy":1.329986572265625,"a":1,"skewX":0,"skewY":0,"0":{"index":2,"0":{"x":-99.2,"y":-22.05,"name":"ref","type":"sprite","r":0,"sx":1,"sy":1,"a":0,"skewX":0,"skewY":0,"0":{"type":"shape","path":[255,0,90.9,2,80.4,90.9,2,80.4,0,2,0,0,2,0,90.9,2,0,90.9,1,1,16777215,33]}},"1":{"type":"bitmap","libName":"镊子_qc.png","x":-99.2,"y":-91.65,"r":0,"sx":1,"sy":1,"skewX":0,"skewY":0}},"1":{"index":1,"0":{"x":-0.95,"y":-2.7,"name":"a","type":"sprite","r":0,"sx":1,"sy":1,"a":1,"skewX":0,"skewY":0,"0":{"type":"bitmap","libName":"Bitmap 5","x":-103.05,"y":-94.65,"r":0,"sx":1,"sy":1,"skewX":0,"skewY":0},"1":{"x":-121.8,"y":43.95,"name":"tone","type":"sprite","r":-0.31369081532323434,"sx":0.817901611328125,"sy":0.817901611328125,"a":1,"skewX":-0.31369081532323434,"skewY":-0.31369081532323434,"0":{"x":55.25,"y":22,"name":"a2","type":"sprite","r":0,"sx":1,"sy":1,"a":1,"skewX":0,"skewY":0,"0":{"type":"bitmap","libName":"Bitmap 198","x":0,"y":0,"r":0,"sx":1,"sy":1,"skewX":0,"skewY":0}},"1":{"x":50.35,"y":-1,"name":"a1","type":"sprite","r":0,"sx":1,"sy":1,"a":1,"skewX":0,"skewY":0,"0":{"type":"bitmap","libName":"Bitmap 199","x":0,"y":0,"r":0,"sx":1,"sy":1,"skewX":0,"skewY":0}},"2":{"x":46.5,"y":-26.2,"name":"a0","type":"sprite","r":0,"sx":1,"sy":1,"a":1,"skewX":0,"skewY":0,"0":{"type":"bitmap","libName":"Bitmap 200","x":0,"y":0,"r":0,"sx":1,"sy":1,"skewX":0,"skewY":0}}},"2":{"x":-63.3,"y":35.95,"name":"back","type":"sprite","r":-0.31369081532323434,"sx":0.817901611328125,"sy":0.817901611328125,"a":1,"skewX":-0.31369081532323434,"skewY":-0.31369081532323434,"0":{"x":3.95,"y":24.7,"name":"w2","type":"sprite","r":0,"sx":1,"sy":1,"a":1,"skewX":0,"skewY":0,"0":{"type":"bitmap","libName":"Bitmap 201","x":-18.3,"y":-13.25,"r":0,"sx":1,"sy":1,"skewX":0,"skewY":0}},"1":{"x":0,"y":0.7,"name":"w1","type":"sprite","r":0,"sx":1,"sy":1,"a":1,"skewX":0,"skewY":0,"0":{"type":"bitmap","libName":"Bitmap 202","x":-18.5,"y":-11.75,"r":0,"sx":1,"sy":1,"skewX":0,"skewY":0}},"2":{"x":-3.95,"y":-24.5,"name":"w0","type":"sprite","r":0,"sx":1,"sy":1,"a":1,"skewX":0,"skewY":0,"0":{"type":"bitmap","libName":"Bitmap 203","x":-18.3,"y":-13.45,"r":0,"sx":1,"sy":1,"skewX":0,"skewY":0}}},"3":{"type":"bitmap","libName":"Bitmap 4","x":-87.5,"y":-77.65,"r":0,"sx":1,"sy":1,"skewX":0,"skewY":0}}}},"9":{"x":576.35,"y":986,"name":"tone","type":"sprite","r":0,"sx":1.329986572265625,"sy":1.329986572265625,"a":1,"skewX":0,"skewY":0,"0":{"type":"bitmap","libName":"石灰岩_big_qc.png","x":0,"y":0,"r":0,"sx":0.3336334228515625,"sy":0.3336334228515625,"skewX":0,"skewY":0}}},"4":{"x":279.75,"y":1328.5,"name":"timeline","type":"sprite","r":0,"sx":1.15997314453125,"sy":1.15997314453125,"a":1,"skewX":0,"skewY":0,"0":{"x":0,"y":0,"name":"drag","type":"sprite","r":0,"sx":1,"sy":1,"a":1,"skewX":0,"skewY":0,"0":{"type":"bitmap","libName":"hitArea","x":-24.5,"y":-23,"r":0,"sx":1.8399658203125,"sy":1.8399658203125,"skewX":0,"skewY":0},"1":{"type":"bitmap","libName":"circle_1","x":0,"y":0,"r":0,"sx":1,"sy":1,"skewX":0,"skewY":0}},"1":{"x":-36.5,"y":69,"w":124.2,"h":43.6,"name":"","type":"text","r":0,"txt":"冷热作用","a":"center","f":"30px 'Microsoft YaHei'","c":"#FFFFFF"},"2":{"x":536.2,"y":69,"w":124.2,"h":43.6,"name":"","type":"text","r":0,"txt":"动物作用","a":"center","f":"30px 'Microsoft YaHei'","c":"#FFFFFF"},"3":{"x":345.3,"y":69,"w":124.2,"h":43.6,"name":"","type":"text","r":0,"txt":"植物作用","a":"center","f":"30px 'Microsoft YaHei'","c":"#FFFFFF"},"4":{"x":154.4,"y":69,"w":124.2,"h":43.6,"name":"","type":"text","r":0,"txt":"流水作用","a":"center","f":"30px 'Microsoft YaHei'","c":"#FFFFFF"},"5":{"x":573.6,"y":0,"name":"a3","type":"sprite","r":0,"sx":1,"sy":1,"a":1,"skewX":0,"skewY":0,"0":{"type":"bitmap","libName":"hitArea","x":-24.5,"y":-23,"r":0,"sx":1.8399658203125,"sy":1.8399658203125,"skewX":0,"skewY":0},"1":{"type":"bitmap","libName":"circle_2","x":0,"y":0,"r":0,"sx":1,"sy":1,"skewX":0,"skewY":0}},"6":{"x":382.4,"y":0,"name":"a2","type":"sprite","r":0,"sx":1,"sy":1,"a":1,"skewX":0,"skewY":0,"0":{"type":"bitmap","libName":"hitArea","x":-24.5,"y":-23,"r":0,"sx":1.8399658203125,"sy":1.8399658203125,"skewX":0,"skewY":0},"1":{"type":"bitmap","libName":"circle_2","x":0,"y":0,"r":0,"sx":1,"sy":1,"skewX":0,"skewY":0}},"7":{"x":191.2,"y":0,"name":"a1","type":"sprite","r":0,"sx":1,"sy":1,"a":1,"skewX":0,"skewY":0,"0":{"type":"bitmap","libName":"hitArea","x":-24.5,"y":-23,"r":0,"sx":1.8399658203125,"sy":1.8399658203125,"skewX":0,"skewY":0},"1":{"type":"bitmap","libName":"circle_2","x":0,"y":0,"r":0,"sx":1,"sy":1,"skewX":0,"skewY":0}},"8":{"x":0,"y":0,"name":"a0","type":"sprite","r":0,"sx":1,"sy":1,"a":1,"skewX":0,"skewY":0,"0":{"type":"bitmap","libName":"hitArea","x":-24.5,"y":-23,"r":0,"sx":1.8399658203125,"sy":1.8399658203125,"skewX":0,"skewY":0},"1":{"type":"bitmap","libName":"circle_2","x":0,"y":0,"r":0,"sx":1,"sy":1,"skewX":0,"skewY":0}}}},{"name":"ei","x":0,"y":0,"type":"sprite"},{"name":"ee","x":0,"y":0,"type":"sprite"},{"name":"cc","x":0,"y":0,"type":"sprite"}]